Workbook

Sheet Definitions
B2: Indicator | C2: Definition
B3: Current Electricity Access Rate (%) | C3: Percentage of the total population with access to electricity
B4: Current Urban Electricity Access Rate (%) | C4: Percentage of the urban population with access to electricity.
B5: Current Rural Electricity Access Rate (%) | C5: Percentage of the rural population with access to electricity.
B6: Target Electricity Access Rate by 2030 (%) | C6: Planned percentage of the population with electricity access by 2030.
B7: Target Urban Electricity Access Rate by 2030 (%) | C7: Planned percentage of the urban population with electricity access by 2030.
B8: Target Rural Electricity Access Rate by 2030 (%) | C8: Planned percentage of the rural population with electricity access by 2030.
B9: Population Without Electricity (people) | C9: Number of people without access to electricity when explicitly stated.
B10: Installed Capacity – Current (MW) | C10: Total installed electricity generation capacity at time of reporting.
B11: Installed Capacity – 2030 Target (MW) | C11: Planned total installed generation capacity by 2030.
B12: New Generation Required (MW) | C12: Additional generation capacity explicitly stated as required.
B13: Renewable Capacity – Current (MW) | C13: Installed renewable electricity generation capacity.
... B43: Universal Access Target Year | C43: Year universal electricity access is targeted.

Sheet Complete_Data_Quantitative
A1: Category | B1: Indicator | C1: Data Source | D1: Comments | E1: Benin | F1: Botswana | G1: Burundi | H1: Cameroon | I1: Chad | J1: Comoros | K1: Ivory Coast | L1: Democratic Republic of Congo | M1: Ethiopia | N1: Gambia | O1: Ghana | P1: Guinea | Q1: Kenya | R1: Lesotho | S1: Liberia | T1: Madagascar | U1: Malawi | V1: Mauritania | W1: Mozambique | X1: Namibia | Y1: Niger | Z1: Nigeria | AA1: Republic of Congo | AB1: São Tomé and Príncipe | AC1: Senegal | AD1: Sierra Leone | AE1: Tanzania | AF1: Togo | AG1: Zambia | AH1: Zimbabwe
A2: Electricity Access | B2: Current Electricity Access Rate (%) | C2: M300 National Energy Compacts | D2: Percentage of the total population that currently has access to electricity through grid or off-grid solutions. | E2: 42.6 | F2: 76.6 | G2: 25.9 | H2: 74 | I2: 11 | J2: 95 | K2: 64 | L2: 21.5 | M2: 44 | N2: 73.7 | O2: 89 | P2: 53 | Q2: 75 | R2: 53 | S2: 32.7 | T2: 36 | U2: 25.9 | V2: 55 | W2: 60.1 | X2: 59.5 | Y2: 20.84 | Z2: 61 | AA2: 31.66 | AB2: 84 | AC2: 84 | AD2: 36 | AE2: 78.4 | AF2: 70 | AG2: 53.6 | AH2: 62
B3: Current Urban Electricity Access Rate (%) | C3: M300 National Energy Compacts | D3: Share of the urban population with access to electricity. | E3: 71.2 | F3: 90 | G3: 66.3 | H3: 94 | I3: 20 | J3: 80 | L3: 60.8 | N3: 97 | P3: 89 | R3: 71.3 | S3: 50 | T3: 72 | U3: 56.5 | V3: 91 | X3: 77.1 | AA3: 38.67 | AC3: 97.1 | AE3: 99.6 | AG3: 80.3 | AH3: 83
B4: Current Rural Electricity Access Rate (%) | C4: M300 National Energy Compacts | D4: Share of the rural population with access to electricity. | E4: 13.1 | G4: 17.6 | H4: 25 | I4: 1 | J4: 20 | L4: 5 | M4: 57 | N4: 45 | P4: 21 | R4: 11.4 | S4: 10 | T4: 11 | U4: 3.8 | V4: 6 | X4: 13.8 | Y4: 5.3 | AA4: 1.01 | AC4: 64.5 | AE4: 69.6 | AG4: 34.9 | AH4: 27
B5: Target Electricity Access Rate by 2030 (%) | C5: M300 National Energy Compacts | D5: Percentage of the population targeted to have electricity access by 2030. | E5: 70 | F5: 100 | G5: 70 | H5: 100 | I5: 90 | J5: 100 | K5: 100 | L5: 62 | M5: 75 | N5: 100 | O5: 99.8 | P5: 100 | Q5: 100 | R5: 100 | S5: 75 | T5: 80 | U5: 70 | V5: 100 | W5: 100 | X5: 70 | Y5: 60 | Z5: 100 | AA5: 81.3 | AB5: 100 | AC5: 100 | AD5: 78 | AE5: 100 | AF5: 100 | AG5: 100 | AH5: 100
B6: Target Urban Electricity Access Rate by 2030 (%) | C6: M300 National Energy Compacts | D6: Electricity access rate targeted for urban areas by 2030. | I6: 50 | U6: 59.5 | V6: 98 | AA6: 90
B7: Target Rural Electricity Access Rate by 2030 (%) | C7: M300 National Energy Compacts | D7: Electricity access rate targeted for rural areas by 2030. | I7: 40 | U7: 24.1 | V7: 80 | AA7: 50 | AG7: 51
B8: Population Without Electricity (people) | C8: M300 National Energy Compacts | D8: Number of people currently living without electricity access. | G8: 11600000 | H8: 33000000 | I8: 14000000 | J8: 226615 | L8: 60000000 | N8: 633000 | O8: 3700000 | P8: 7750000 | T8: 19000000 | V8: 3400000 | Z8: 86000000 | AC8: 2800000
A9: Generation Capacity & Supply Mix | B9: Installed Capacity – Current (MW) | C9: M300 National Energy Compacts | D9: Total electricity generation capacity currently installed and operational. | E9: 199.8 | F9: 892 | G9: 204.88 | H9: 3000 | I9: 487 | J9: 53 | K9: 2907 | L9: 3067 | M9: 9761 | N9: 99 | O9: 5641 | P9: 1310 | Q9: 2627 | R9: 104.7 | S9: 126 | T9: 828 | U9: 550 | V9: 615.1 | W9: 2922 | X9: 695 | Y9: 352 | Z9: 12000 | AA9: 748 | AB9: 38 | AD9: 271 | AE9: 3404.2 | AF9: 267.5 | AG9: 3811.3 | AH9: 2962
B10: Installed Capacity – 2030 Target (MW) | C10: M300 National Energy Compacts | D10: Total generation capacity planned to be installed by 2030. | E10: 794 | F10: 950 | G10: 410 | H10: 3000 | I10: 866 | K10: 5128 | L10: 13576 | M10: 14000 | O10: 6200 | P10: 3827 | Q10: 5952 | U10: 1490 | X10: 1149 | AA10: 3701 | AD10: 1120 | AF10: 1154.5 | AG10: 10000 | AH10: 5432
B11: New Generation Required (MW) | C11: M300 National Energy Compacts | D11: Additional generation capacity required to meet future demand and access targets. | I11: 866 | K11: 1374 | P11: 2517 | Q11: 3325 | U11: 848 | W11: 3100 | X11: 454 | AA11: 2953 | AB11: 60 | AE11: 1973 | AF11: 894 | AG11: 6200
B12: Renewable Capacity – Current (MW) | C12: M300 National Energy Compacts | D12: Installed electricity generation capacity from renewable energy sources. | E12: 62.3 | F12: 74.6 | H12: 36.53 | J12: 13.71 | K12: 909 | N12: 23 | O12: 60.8 | P12: 817 | R12: 104.3 | S12: 88 | T12: 240 | U12: 499 | W12: 2291 | X12: 498.5 | AA12: 214 | AC12: 460 | AE12: 2011.27 | AF12: 102.5 | AG12: 3336 | AH12: 1282
B13: Renewable Capacity – 2030 Target (MW) | C13: M300 National Energy Compacts | D13: Renewable energy generation capacity targeted by 2030. | E13: 417 | F13: 475 | I13: 520 | K13: 2283 | P13: 2689 | S13: 238 | T13: 893 | W13: 4892 | X13: 952.5 | AA13: 2697 | AF13: 728.5 | AG13: 9000 | AH13: 2640
B14: Solar Capacity Target (MW) | C14: M300 National Energy Compacts | D14: Planned installed solar power capacity by 2030. | F14: 1500 | G14: 254 | H14: 150 | I14: 520 | K14: 399 | L14: 4000 | M14: 1175 | N14: 150 | O14: 850 | P14: 1086 | Q14: 807 | R14: 164 | S14: 172 | T14: 560 | V14: 50 | W14: 303 | X14: 466.5 | AD14: 392 | AE14: 463 | AF14: 569 | AG14: 3000 | AH14: 1500
B15: Wind Capacity Target (MW) | C15: M300 National Energy Compacts | D15: Planned installed wind power capacity by 2030. | F15: 100 | M15: 1102 | O15: 200 | Q15: 966 | R15: 60 | T15: 16 | V15: 30 | W15: 245 | X15: 99 | Y15: 250 | AE15: 500 | AG15: 1192
B16: Hydro Capacity Target (MW) | C16: M300 National Energy Compacts | D16: Planned installed hydropower capacity by 2030. | G16: 155.5 | H16: 600 | I16: 120 | J16: 1.95 | K16: 829 | M16: 1800 | O16: 150 | P16: 791 | Q16: 1403 | R16: 1.1 | S16: 150 | T16: 374 | W16: 4344 | X16: 347 | Y16: 128 | AB16: 9 | AD16: 194 | AE16: 880 | AF16: 57
B17: Gas Capacity Target (MW) | C17: M300 National Energy Compacts | D17: Planned installed gas-fired generation capacity by 2030. | N17: 80 | V17: 225 | W17: 1004 | Y17: 240 | AA17: 470 | AB17: 10 | AC17: 2200 | AF17: 250
B18: Battery Storage Target (MWh) | C18: M300 National Energy Compacts | D18: Planned electricity storage capacity to support grid stability and renewable integration. | F18: 140 | I18: 60 | J18: 19.6 | N18: 40 | Q18: 400 | R18: 600 | S18: 5 | V18: 30 | X18: 96 | Y18: 20 | AF18: 156
A19: Demand | B19: Peak Demand – Current (MW) | C19: M300 National Energy Compacts | D19: Highest electricity demand currently observed on the power system. | F19: 678 | J19: 26.2 | R19: 209 | S19: 108 | X19: 673 | AD19: 320 | AE19: 1888.72 | AG19: 2500 | AH19: 2000
B20: Peak Demand – 2030 (MW) | C20: M300 National Energy Compacts | D20: Projected maximum electricity demand expected by 2030. | P20: 3894 | U20: 774 | AD20: 485
A21: Networks & Losses | B21: Transmission Lines – Existing (km) | C21: M300 National Energy Compacts | D21: Total length of existing high-voltage transmission lines. | E21: 1449.1 | F21: 4000 | G21: 650 | I21: 996 | K21: 7553 | M21: 20390 | N21: 18 | O21: 6472.2 | P21: 1600 | Q21: 9484 | S21: 1398 | U21: 2650 | V21: 1950 | W21: 5679 | Y21: 1428.8 | Z21: 12330 | AA21: 1756 | AB21: 275 | AD21: 802 | AE21: 8025.75 | AF21: 1273 | AG21: 12705
B22: Transmission Lines – Added (km) | C22: M300 National Energy Compacts | D22: Additional transmission lines planned for construction. | G22: 704 | I22: 400.2 | K22: 10212 | N22: 200 | P22: 352 | Q22: 8000 | U22: 1940 | V22: 2550 | W22: 2000 | AD22: 1235 | AF22: 1447 | AG22: 17913 | AH22: 1607
B23: Distribution Lines – Added (km) | C23: M300 National Energy Compacts | D23: Additional electricity distribution network lines planned. | G23: 6578 | I23: 195 | K23: 93848 | Q23: 212937 | R23: 550 | U23: 22417 | V23: 4550 | AC23: 39000 | AF23: 3761
B24: System Losses – Current (%) | C24: M300 National Energy Compacts | D24: Percentage of electricity lost through technical and non-technical losses. | E24: 24.62 | F24: 14.35 | I24: 39 | J24: 37 | L24: 46 | M24: 27 | N24: 21 | O24: 27 | P24: 30 | Q24: 15.69 | S24: 45.4 | T24: 30 | V24: 30 | W24: 24 | Z24: 42 | AA24: 45 | AB24: 34 | AD24: 50 | AE24: 14.2 | AF24: 16
B25: Efficiency - System Losses (%) | C25: World Bank UPBEAT Database | D25: Power system efficiency expressed as the inverse of system losses. | E25: 24 | F25: 15.35 | G25: 19.22 | I25: 37 | K25: 14.98 | L25: 31.2 | N25: 17.6 | P25: 19 | Q25: 23 | R25: 12.87 | S25: 32 | T25: 27.38 | U25: 20.99 | V25: 22.92 | W25: 26 | Y25: 23.55 | AB25: 24.3 | AC25: 17.7 | AE25: 14.49 | AF25: 16.04 | AH25: 17.5
B26: System Losses – Target (%) | C26: M300 National Energy Compacts | D26: Targeted reduction level of system losses by 2030. | E26: 15 | H26: 10 | I26: 15 | J26: 20 | L26: 15 | M26: 19 | N26: 18 | O26: 23 | P26: 8 | Q26: 12.8 | T26: 16 | V26: 20 | AB26: 18 | AF26: 12
A27: Connections | B27: Grid Connections – New (connections) | C27: M300 National Energy Compacts | D27: Number of new electricity connections planned through the national grid. | E27: 928000 | F27: 220000 | G27: 1900000 | H27: 8000000 | I27: 17500000 | J27: 62310 | K27: 3070000 | L27: 60000000 | M27: 6461000 | N27: 20000 | O27: 660000 | P27: 7750000 | Q27: 5100000 | R27: 26400 | S27: 100000 | T27: 3500000 | U27: 1150000 | V27: 3389524 | W27: 4900000 | X27: 175000 | Y27: 2077515 | Z27: 4700000 | AA27: 953000 | AB27: 8000 | AC27: 260149 | AD27: 160000 | AE27: 8300000 | AF27: 1300000 | AG27: 1459560 | AH27: 1200000
B28: Grid Connections – New (HH) | C28: M300 National Energy Compacts | D28: Number of households planned to be newly connected to the grid. | O28: 660000 | X28: 175000 | AD28: 160000 | AE28: 8300000
B29: Off-grid Connections Target (connections) | C29: M300 National Energy Compacts | D29: Total number of electricity connections planned through off-grid solutions. | F29: 61000 | G29: 410000 | I29: 20000 | J29: 3739 | K29: 5800000 | R29: 18900 | S29: 40000 | U29: 1550000 | V29: 1054204 | W29: 435000 | X29: 35000 | Y29: 115301 | Z29: 93193 | AB29: 800 | AD29: 560000 | AF29: 133000 | AG29: 1768311 | AH29: 1500000
B30: Off-grid Connections Target (Mini-grids) | C30: M300 National Energy Compacts | D30: Number of off-grid connections provided via mini-grids. | M30: 2769000 | T30: 200 | Y30: 115301 | AC30: 1600000
B31: Off-grid Connections Target (Solar kits) | C31: M300 National Energy Compacts | D31: Number of off-grid connections provided via solar home systems. | V31: 435249 | Y31: 690392 | Z31: 2930000 | AC31: 1200000 | AJ31: =ISBLANK -> #NAME?
B32: Off-grid Connections Target (HH) | C32: M300 National Energy Compacts | D32: Number of households expected to gain off-grid electricity access. | X32: 35000 | AB32: 800 | AD32: 560000
B33: Mini-grid Sites Target (count) | C33: M300 National Energy Compacts | D33: Number of mini-grid installations planned. | F33: 6 | G33: 300 | O33: 400 | P33: 714 | Q33: 199048 | R33: 11 | U33: 3 | V33: 120 | W33: 98 | Y33: 115301 | Z33: 158 | AC33: 150 | AD33: 100 | AE33: 68
B34: Mini-grid Capacity Target (MW) | C34: M300 National Energy Compacts | D34: Total electricity generation capacity of planned mini-grids. | G34: 300 | O34: 0.24 | W34: 11.6 | AC34: 50 | AD34: 40
B35: SHS Connections Target (connections) | C35: M300 National Energy Compacts | D35: Number of Solar Home System connections targeted. | G35: 850000 | I35: 30000 | O35: 1000000 | P35: 1326 | S35: 49441 | U35: 244000 | W35: 175235 | Y35: 690392 | AB35: 800 | AC35: 300000 | AD35: 400000 | AF35: 133000
A36: Finance | B36: Total Investment Required (USD) | C36: M300 National Energy Compacts | D36: Total estimated investment required to achieve electricity and clean cooking targets. | E36: 2360000000 | F36: 2520000000 | G36: 3490000000 | H36: 12554000000 | I36: 1950000000 | J36: 390210000 | K36: 6560000000 | L36: 37048660000 | M36: 9646040000 | N36: 552000000 | O36: 4404000000 | P36: 8900000000 | Q36: 18730000000 | R36: 1970000000 | S36: 1250000000 | T36: 7200000000 | U36: 5500000000 | V36: 2450000000 | W36: 18620000000 | X36: 1764000000 | Z36: 32700000000 | AA36: 11543000000 | AB36: 297000000 | AC36: 6300000000 | AD36: 2245000000 | AE36: 12889999999 | AF36: 3000000000 | AG36: 11880000000 | AH36: 9134890000
B37: Public Financing Required (USD) | C37: M300 National Energy Compacts | D37: Portion of total investment expected from public funding sources. | E37: 1420000000 | F37: 1414000000 | G37: 1950000000 | I37: 1299744000 | J37: 117000000 | K37: 4620000000 | L37: 17314100000 | M37: 6584240000 | N37: 305000000 | O37: 1793000000 | P37: 1200000000 | Q37: 10820000000 | R37: 499700000 | T37: 2880000000 | W37: 9923000000 | X37: 1353000000 | Z37: 17200000000 | AA37: 3276000000 | AB37: 108000000 | AD37: 835000000 | AE37: 8850000000 | AF37: 1320000000
B38: Private Financing Required (USD) | C38: M300 National Energy Compacts | D38: Portion of total investment expected from private sector financing. | E38: 940000000 | F38: 1106000000 | G38: 1540000000 | H38: 6372000000 | I38: 650256000 | J38: 273000000 | K38: 1940000000 | L38: 19734550000 | M38: 3061800000 | N38: 247000000 | O38: 2611000000 | P38: 7641000000 | Q38: 7910000000 | R38: 1470000000 | S38: 150000000 | T38: 4320000000 | U38: 162800000 | V38: 1230000000 | W38: 8698000000 | X38: 411000000 | Y38: 527000000 | Z38: 15500000000 | AA38: 8267000000 | AB38: 190000000 | AC38: 2300000000 | AD38: 1410000000 | AE38: 4039000000 | AF38: 1680000000 | AG38: 9500000000 | AH38: 4420000000
B39: World Bank Financing (USD) | C39: M300 National Energy Compacts | D39: Expected financing contribution from the World Bank. | O39: 260000000 | R39: 52900000 | S39: 200000000
B40: AfDB Financing (USD) | C40: M300 National Energy Compacts | D40: Expected financing contribution from the African Development Bank. | O40: 85000000 | R40: 10600000
B41: Other Donor Financing (USD) | C41: M300 National Energy Compacts | D41: Financing expected from other development partners and donors. | J41: 101400000 | P41: 7600000000 | T41: 1150000000 | U41: 530800000 | V41: 621240000
A42: Utility & Tariffs | B42: Average Tariff (USD/kWh) | C42: M300 National Energy Compacts | D42: Average electricity price charged per kilowatt-hour. | I42: 0.18 | J42: 0.43 | L42: 0.09 | N42: 0.21 | P42: 0.1 | S42: 0.23 | T42: 0.28 | Y42: 0.14 | Z42: 0.09 | AA42: 0.09 | AD42: 0.21 | AE42: 0.089 | AH42: 0.1608
B43: Cost Recovery Ratio current | C43: M300 National Energy Compacts | D43: Ratio of utility revenues collected to total costs incurred. | J43: 56.6 | M43: 60 | P43: 45 | S43: 63 | U43: 100 | V43: 77.47 | AA43: 0.56 | AC43: 0.72 | AE43: 80
B44: Operating and debt service cost recovery, excluding subsidies (%) | C44: World Bank UPBEAT Database | D44: Share of operating and debt service costs covered by revenues without subsidies. | E44: 103.49461 | F44: 72.454149 | G44: 102.98416 | I44: 127.73934 | J44: 93.153884 | L44: 65.858882 | M44: 122.53822 | N44: 82.678692 | O44: 22.513461 | P44: 8.2733733 | Q44: 106.23327 | R44: 102.00067 | S44: 70.552905 | T44: 39.89032 | U44: 87.409377 | V44: 57.03032 | W44: 129.372 | X44: 108.27087 | Y44: 76.14838 | Z44: 123.99895 | AC44: 60.586429 | AD44: 55.650095 | AE44: 98.734936 | AF44: 81.213932 | AG44: 106.79471 | AH44: 83.650698
B45: Cost Recovery Ratio target | C45: M300 National Energy Compacts | D45: Targeted cost recovery level to be achieved by the utility. | E45: 100 | F45: 100 | G45: 100 | V45: 100 | X45: 100 | AF45: 100 | AH45: 1
B46: Utility Collection Rate - Current (%) | C46: M300 National Energy Compacts | D46: Percentage of billed electricity revenues currently collected. | H46: 72 | I46: 51 | J46: 80 | L46: 61 | O46: 86 | T46: 80 | AA46: 73 | AD46: 40 | AE46: 96
B47: Liquidity - Collection Rate (%) | C47: World Bank UPBEAT Database | D47: Measure of utility cash flow adequacy based on revenue collection. | E47: 86.56 | F47: 91.41 | G47: 99.66 | I47: 282.3 | J47: 97.36 | K47: 55.24 | L47: 89.71 | M47: 107.36 | N47: 97.85 | O47: 39.64 | P47: 35.63 | Q47: 97.68 | R47: 96.52 | S47: 81.73 | T47: 90.47 | U47: 98.04 | V47: 93.75 | W47: 116.41 | X47: 102.9 | Y47: 102.8 | Z47: 62.92 | AB47: 78.13 | AC47: 90.62 | AD47: 80.65 | AE47: 97.9 | AF47: 95.64 | AG47: 96.15 | AH47: 77.5
B48: Utility Collection Rate - Target (%) | C48: M300 National Energy Compacts | D48: Targeted electricity bill collection rate. | E48: 95 | H48: 90 | I48: 45 | J48: 90 | L48: 100 | M48: 90 | R48: 100 | S48: 100 | T48: 90 | U48: 100 | W48: 100 | Z48: 100 | AA48: 95 | AC48: 100 | AD48: 100 | AF48: 100
A49: Renewables, Climate & Efficiency | B49: Renewable Share – Current (%) | C49: M300 National Energy Compacts | D49: Share of electricity generation currently coming from renewable sources. | E49: 16 | F49: 8.2 | G49: 83 | H49: 5 | I49: 9 | J49: 9 | K49: 31 | L49: 95 | M49: 95 | N49: 13 | O49: 4 | P49: 62 | Q49: 83 | R49: 99.6 | S49: 67 | T49: 45 | U49: 90 | V49: 44.36 | W49: 78.4 | X49: 54 | Y49: 5 | Z49: 22 | AA49: 29 | AB49: 5 | AC49: 29 | AD49: 46 | AE49: 61.8 | AF49: 26 | AG49: 86.2 | AH49: 43
B50: Renewable Share – 2030 Target (%) | C50: M300 National Energy Compacts | D50: Targeted renewable energy share in electricity generation by 2030. | E50: 30 | F50: 50 | G50: 99 | H50: 10 | I50: 30 | J50: 45 | K50: 45 | L50: 95 | N50: 30 | O50: 10 | P50: 70 | Q50: 100 | R50: 100 | S50: 75 | T50: 85 | U50: 96.1 | V50: 70 | W50: 80.6 | X50: 70 | Y50: 30 | Z50: 50 | AA50: 72.8 | AB50: 50 | AC50: 40 | AD50: 52 | AE50: 75 | AF50: 63 | AH50: 48.6
B51: CO2 Emissions Reduction (tCO2) | C51: M300 National Energy Compacts | D51: Estimated reduction in carbon dioxide emissions from clean energy measures. | G51: 343720000000 | K51: 6319428 | U51: 4090750 | V51: 1400000
B52: Energy Efficiency Savings (GWh/year) | C52: M300 National Energy Compacts | D52: Annual electricity savings from energy efficiency improvements.
A53: Clean Cooking | B53: Clean cooking access - current (%) | C53: M300 National Energy Compacts | D53: Percentage of the population currently using clean cooking technologies. | E53: 10.5 | F53: 66.6 | H53: 23.4 | J53: 0.5 | K53: 20 | L53: 5 | M53: 8 | N53: 25 | O53: 36.9 | P53: 12 | Q53: 34.4 | R53: 45.2 | S53: 0.8 | T53: 14 | U53: 24.5 | V53: 54 | W53: 17 | X53: 48.5 | Y53: 6 | Z53: 26 | AA53: 39.6 | AB53: 62 | AD53: 1.5 | AE53: 6.9 | AF53: 14 | AG53: 8.9 | AH53: 38.6
B54: Clean cooking access, urban - current (%) | C54: M300 National Energy Compacts | D54: Share of the urban population with access to clean cooking solutions. | F54: 86.9 | X54: 77.1 | AA54: 54.5
B55: Clean cooking access, rural - current (%) | C55: M300 National Energy Compacts | D55: Share of the rural population with access to clean cooking solutions. | F55: 25.3 | X55: 13.8 | AA55: 4.7
B56: Clean cooking access by electricity - current (%) | C56: M300 National Energy Compacts | D56: Share of the population using electricity for clean cooking. | F56: 24.4 | Q56: 1.3 | T56: 1 | U56: 1.7 | Z56: 1 | AB56: 0.08 | AC56: 0.1 | AD56: 0 | AG56: 15.8
B57: Clean cooking access by biogas - current (%) | C57: M300 National Energy Compacts | D57: Share of the population using biogas for clean cooking. | Q57: 0.3 | T57: 1 | U57: 0
B58: Clean cooking access by LPG - current (%) | C58: M300 National Energy Compacts | D58: Share of the population using liquefied petroleum gas for cooking. | F58: 42.7 | K58: 20 | L58: 2 | O58: 31 | P58: 1 | Q58: 30.7 | T58: 1 | U58: 0.3 | W58: 14 | X58: 21.8 | Y58: 4.6 | Z58: 10.5 | AB58: 18.9 | AC58: 34 | AD58: 0.9 | AE58: 3.2 | AF58: 11 | AG58: 0.3
B59: Clean cooking access by bioethanol - current (%) | C59: M300 National Energy Compacts | D59: Share of the population using bioethanol for cooking. | Q59: 1.8 | T59: 1 | U59: 0 | AD59: 0 | AG59: 0.1
B60: Clean cooking access by other technologies - current (%) | C60: M300 National Energy Compacts | D60: Share of the population using other clean cooking technologies. | W60: 3.4
B61: Clean cooking access - 2030 target (%) | C61: M300 National Energy Compacts | D61: Targeted clean cooking access rate by 2030. | E61: 50 | F61: 90 | G61: 40 | H61: 40 | I61: 46 | J61: 30 | K61: 50 | L61: 30 | M61: 57.74 | N61: 50 | O61: 50 | P61: 35 | Q61: 100 | R61: 75 | T61: 50 | U61: 75 | W61: 54 | X61: 61 | Y61: 12 | Z61: 100 | AA61: 81.3 | AB61: 75 | AD61: 25 | AE61: 75 | AF61: 80 | AG61: 40 | AH61: 70
B62: Clean cooking access - 2030 target (persons) | C62: M300 National Energy Compacts | D62: Number of people expected to have clean cooking access by 2030. | J62: 318467
B63: Population with clean cooking access (%) | C63: M300 National Energy Compacts | D63: Share of total population with access to clean cooking solutions. | F63: 66 | O63: 36.9 | P63: 12 | Q63: 34.4 | R63: 45.2 | S63: 0.8 | T63: 14 | U63: 24.5 | V63: 54 | W63: 17 | X63: 48.5 | Y63: 4.6 | Z63: 26 | AA63: 39.6 | AB63: 62 | AD63: 25 | AE63: 6.9 | AF63: 80
B64: Total people with clean cooking access (additional persons) | C64: M300 National Energy Compacts | D64: Number of additional people gaining clean cooking access. | G64: 6000000 | H64: 13400000 | L64: 40000000 | O64: 3100000 | P64: 4100000 | Q64: 4800000 | S64: 9545 | T64: 4100000 | AC64: 15800000 | AF64: 2000000
B65: Total people with clean cooking access (households) | C65: M300 National Energy Compacts | D65: Number of households newly benefiting from clean cooking access. | E65: 1285000 | F65: 420000 | G65: 1200000 | I65: 5500000 | K65: 2400000 | L65: 5000000 | Q65: 15000000 | T65: 800000 | V65: 480000 | W65: 4500000 | X65: 200000 | AD65: 900000
A66: Electricity Access (derived) | B66: Current electricity access gap (million) | D66: Number of people currently without electricity access. | E66: ='Copy of Derived_Data_Quantitati'!D31 -> 8.323 | F66: ='Copy of Derived_Data_Quantitati'!E31 -> 0.585 | G66: ='Copy of Derived_Data_Quantitati'!F31 -> 10.374 | H66: ='Copy of Derived_Data_Quantitati'!G31 -> 7.566 | I66: ='Copy of Derived_Data_Quantitati'!H31 -> 18.067 | J66: ='Copy of Derived_Data_Quantitati'!I31 -> 0.045 | K66: ='Copy of Derived_Data_Quantitati'!J31 -> 11.484 | L66: ='Copy of Derived_Data_Quantitati'!K31 -> 85.8005 | ... AD66: ='Copy of Derived_Data_Quantitati'!AC31 -> 5.504 | AE66: ='Copy of Derived_Data_Quantitati'!AE31 -> 14.8176 | AF66: ='Copy of Derived_Data_Quantitati'!AD31 -> 2.85 | AG66: ='Copy of Derived_Data_Quantitati'!AF31 -> 9.8832 | AH66: ='Copy of Derived_Data_Quantitati'!AG31 -> 6.308
B67: 2030 electricity access gap (million) | D67: Projected number of people without electricity access in 2030. | E67: ='Copy of Derived_Data_Quantitati'!D32 -> 4.986 | F67: ='Copy of Derived_Data_Quantitati'!E32 -> 0 | G67: ='Copy of Derived_Data_Quantitati'!F32 -> 4.854 | H67: ='Copy of Derived_Data_Quantitati'!G32 -> 0 | I67: ='Copy of Derived_Data_Quantitati'!H32 -> 2.421 | J67: ='Copy of Derived_Data_Quantitati'!I32 -> 0 | K67: ='Copy of Derived_Data_Quantitati'!J32 -> 0 | L67: ='Copy of Derived_Data_Quantitati'!K32 -> 49.9814 | ... AD67: ='Copy of Derived_Data_Quantitati'!AC32 -> 2.1318 | AE67: ='Copy of Derived_Data_Quantitati'!AE32 -> 0 | AF67: ='Copy of Derived_Data_Quantitati'!AD32 -> 0 | AG67: ='Copy of Derived_Data_Quantitati'!AF32 -> 0 | AH67: ='Copy of Derived_Data_Quantitati'!AG32 -> 0
B68: Electricity access gap reduction, 2024-2030 (million) | D68: Reduction in the electricity access gap between 2024 and 2030. | E68: ='Copy of Derived_Data_Quantitati'!D35 -> 3.337 | F68: ='Copy of Derived_Data_Quantitati'!E35 -> 0.585 | G68: ='Copy of Derived_Data_Quantitati'!F35 -> 5.52 | H68: ='Copy of Derived_Data_Quantitati'!G35 -> 7.566 | I68: ='Copy of Derived_Data_Quantitati'!H35 -> 15.646 | J68: ='Copy of Derived_Data_Quantitati'!I35 -> 0.045 | K68: ='Copy of Derived_Data_Quantitati'!J35 -> 11.484 | L68: ='Copy of Derived_Data_Quantitati'!K35 -> 35.8191 | ... AD68: ='Copy of Derived_Data_Quantitati'!AC35 -> 3.3722 | AE68: ='Copy of Derived_Data_Quantitati'!AE35 -> 14.8176 | AF68: ='Copy of Derived_Data_Quantitati'!AD35 -> 2.85 | AG68: ='Copy of Derived_Data_Quantitati'!AF35 -> 9.8832 | AH68: ='Copy of Derived_Data_Quantitati'!AG35 -> 6.308
B69: Electricity access population increase, 2024-2030 (million) | D69: Number of people expected to gain electricity access during 2024–2030. | E69: ='Copy of Derived_Data_Quantitati'!D29 -> 5.457 | F69: ='Copy of Derived_Data_Quantitati'!E29 -> 0.855 | G69: ='Copy of Derived_Data_Quantitati'!F29 -> 7.7 | H69: ='Copy of Derived_Data_Quantitati'!G29 -> 12.246 | I69: ='Copy of Derived_Data_Quantitati'!H29 -> 19.556 | J69: ='Copy of Derived_Data_Quantitati'!I29 -> 0.105 | K69: ='Copy of Derived_Data_Quantitati'!J29 -> 16.284 | L69: ='Copy of Derived_Data_Quantitati'!K29 -> 58.0491 | ... AD69: ='Copy of Derived_Data_Quantitati'!AC29 -> 4.4622 | AE69: ='Copy of Derived_Data_Quantitati'!AE29 -> 27.1276 | AF69: ='Copy of Derived_Data_Quantitati'!AD29 -> 4.14 | AG69: ='Copy of Derived_Data_Quantitati'!AF29 -> 13.6032 | AH69: ='Copy of Derived_Data_Quantitati'!AG29 -> 8.318
A70: Clean Cooking Access (derived) | B70: Current clean cooking access gap (million) | D70: Number of people currently without clean cooking access. | E70: ='Copy of Derived_Data_Quantitati'!D31 -> 8.323 | F70: ='Copy of Derived_Data_Quantitati'!E31 -> 0.585 | G70: ='Copy of Derived_Data_Quantitati'!F31 -> 10.374 | H70: ='Copy of Derived_Data_Quantitati'!G31 -> 7.566 | I70: ='Copy of Derived_Data_Quantitati'!H31 -> 18.067 | J70: ='Copy of Derived_Data_Quantitati'!I31 -> 0.045 | K70: ='Copy of Derived_Data_Quantitati'!J31 -> 11.484 | L70: ='Copy of Derived_Data_Quantitati'!K31 -> 85.8005 | ... AD70: ='Copy of Derived_Data_Quantitati'!AC31 -> 5.504 | AE70: ='Copy of Derived_Data_Quantitati'!AE31 -> 14.8176 | AF70: ='Copy of Derived_Data_Quantitati'!AD31 -> 2.85 | AG70: ='Copy of Derived_Data_Quantitati'!AF31 -> 9.8832 | AH70: ='Copy of Derived_Data_Quantitati'!AG31 -> 6.308
B71: 2030 clean cooking access gap (million) | D71: Projected clean cooking access gap in 2030. | E71: ='Copy of Derived_Data_Quantitati'!D32 -> 4.986 | F71: ='Copy of Derived_Data_Quantitati'!E32 -> 0 | G71: ='Copy of Derived_Data_Quantitati'!F32 -> 4.854 | H71: ='Copy of Derived_Data_Quantitati'!G32 -> 0 | I71: ='Copy of Derived_Data_Quantitati'!H32 -> 2.421 | J71: ='Copy of Derived_Data_Quantitati'!I32 -> 0 | K71: ='Copy of Derived_Data_Quantitati'!J32 -> 0 | L71: ='Copy of Derived_Data_Quantitati'!K32 -> 49.9814 | ... AD71: ='Copy of Derived_Data_Quantitati'!AC32 -> 2.1318 | AE71: ='Copy of Derived_Data_Quantitati'!AE32 -> 0 | AF71: ='Copy of Derived_Data_Quantitati'!AD32 -> 0 | AG71: ='Copy of Derived_Data_Quantitati'!AF32 -> 0 | AH71: ='Copy of Derived_Data_Quantitati'!AG32 -> 0
B72: Clean cooking access gap reduction, 2024-2030 (million) | D72: Expected reduction in the clean cooking access gap between 2024 and 2030. | E72: ='Copy of Derived_Data_Quantitati'!D35 -> 3.337 | F72: ='Copy of Derived_Data_Quantitati'!E35 -> 0.585 | G72: ='Copy of Derived_Data_Quantitati'!F35 -> 5.52 | H72: ='Copy of Derived_Data_Quantitati'!G35 -> 7.566 | I72: ='Copy of Derived_Data_Quantitati'!H35 -> 15.646 | J72: ='Copy of Derived_Data_Quantitati'!I35 -> 0.045 | K72: ='Copy of Derived_Data_Quantitati'!J35 -> 11.484 | L72: ='Copy of Derived_Data_Quantitati'!K35 -> 35.8191 | ... AD72: ='Copy of Derived_Data_Quantitati'!AC35 -> 3.3722 | AE72: ='Copy of Derived_Data_Quantitati'!AE35 -> 14.8176 | AF72: ='Copy of Derived_Data_Quantitati'!AD35 -> 2.85 | AG72: ='Copy of Derived_Data_Quantitati'!AF35 -> 9.8832 | AH72: ='Copy of Derived_Data_Quantitati'!AG35 -> 6.308
B73: Clean cooking population increase, 2024-2030 (million) | D73: Number of people expected to gain clean cooking access during the period. | E73: ='Copy of Derived_Data_Quantitati'!D30 -> 6.7875 | F73: ='Copy of Derived_Data_Quantitati'!E30 -> 0.828 | G73: ='Copy of Derived_Data_Quantitati'!F30 -> #VALUE! | H73: ='Copy of Derived_Data_Quantitati'!G30 -> 6.7026 | I73: ='Copy of Derived_Data_Quantitati'!H30 -> #VALUE! | J73: ='Copy of Derived_Data_Quantitati'!I30 -> 0.2835 | K73: ='Copy of Derived_Data_Quantitati'!J30 -> 11.97 | L73: ='Copy of Derived_Data_Quantitati'!K30 -> 33.994 | ... AD73: ='Copy of Derived_Data_Quantitati'!AC30 -> 2.2935 | AE73: ='Copy of Derived_Data_Quantitati'!AE30 -> 55.9491 | AF73: ='Copy of Derived_Data_Quantitati'!AD30 -> 7.302 | AG73: ='Copy of Derived_Data_Quantitati'!AF30 -> 8.1123 | AH73: ='Copy of Derived_Data_Quantitati'!AG30 -> 6.6194
A74: Compact Timeline | B74: Compact Start Year | C74: M300 National Energy Compacts | D74: Year in which the national energy compact implementation begins. | E74: 2025 | F74: 2025 | G74: 2025 | H74: 2025 | I74: 2025 | J74: 2025 | K74: 2025 | L74: 2025 | M74: 2024 | N74: 2024 | O74: 2025 | P74: 2025 | Q74: 2025 | R74: 2024 | S74: 2024 | T74: 2024 | U74: 2024 | V74: 2024 | W74: 2024 | X74: 2025 | Y74: 2024 | Z74: 2024 | AA74: 2025 | AB74: 2024 | AC74: 2024 | AD74: 2025 | AE74: 2024 | AF74: 2025 | AG74: 2025 | AH74: 2025
B75: Compact End Year | C75: M300 National Energy Compacts | D75: Year in which the national energy compact implementation ends. | E75: 2030 | F75: 2030 | G75: 2030 | H75: 2030 | I75: 2030 | J75: 2030 | K75: 2030 | L75: 2030 | M75: 2030 | N75: 2030 | O75: 2030 | P75: 2030 | Q75: 2030 | R75: 2030 | S75: 2030 | T75: 2030 | U75: 2030 | V75: 2030 | W75: 2030 | X75: 2030 | Y75: 2030 | Z75: 2030 | AA75: 2030 | AB75: 2030 | AC75: 2030 | AD75: 2030 | AE75: 2030 | AF75: 2030 | AG75: 2030 | AH75: 2030
B76: Universal Access Target Year | C76: M300 National Energy Compacts | D76: Year targeted for achieving universal access to electricity and clean cooking. | E76: 2030 | F76: 2030 | G76: 2030 | H76: 2030 | I76: 2030 | J76: 2030 | K76: 2030 | L76: 2030 | M76: 2030 | N76: 2030 | O76: 2030 | P76: 2030 | Q76: 2030 | R76: 2030 | S76: 2030 | T76: 2030 | U76: 2030 | V76: 2030 | W76: 2030 | X76: 2040 | Y76: 2030 | Z76: 2030 | AA76: 2030 | AB76: 2030 | AC76: 2029 | AD76: 2030 | AE76: 2030 | AF76: 2030 | AG76: 2030 | AH76: 2030
A77: Population | B77: 2024 population (million) | C77: World Bank Open Database | D77: Estimated total population in 2024. | E77: 14.5 | F77: 2.5 | G77: 14 | H77: 29.1 | I77: 20.3 | J77: 0.9 | K77: 31.9 | L77: 109.3 | M77: 132.1 | N77: 2.8 | O77: 34.4 | P77: 14.8 | Q77: 56.4 | R77: 2.3 | S77: 5.6 | T77: 32 | U77: 21.7 | V77: 5.2 | W77: 34.6 | X77: 3 | Y77: 27 | Z77: 232.7 | AA77: 6.3 | AB77: 0.2 | AC77: 18.5 | AD77: 8.6 | AE77: 68.6 | AF77: 9.5 | AG77: 21.3 | AH77: 16.6
B78: 2030 Projected population (million) | C78: UN World Population Prospects | D78: Projected total population in 2030 based on demographic forecasts. | E78: 16.62 | F78: 2.77 | G78: 16.18 | H78: 33.78 | I78: 24.21 | J78: 0.96 | K78: 36.7 | L78: 131.53 | M78: 152.86 | N78: 3.13 | O78: 38.22 | P78: 16.81 | Q78: 63.1 | R78: 2.49 | S78: 6.37 | T78: 36.69 | U78: 25.16 | V78: 6.06 | W78: 40.85 | X78: 3.39 | Y78: 32.52 | Z78: 262.38 | AA78: 7.28 | AB78: 0.26 | AC78: 21.16 | AD78: 9.69 | AE78: 80.91 | AF78: 10.79 | AG78: 25.02 | AH78: 18.61
A79: Date | B79: Last Update | E79: 2025 | F79: 2025 | G79: 2025 | H79: 2025 | I79: 2025 | J79: 2025 | K79: 2025 | L79: 2025 | M79: 2025 | N79: 2025 | O79: 2025 | P79: 2025 | Q79: 2025 | R79: 2025 | S79: 2025 | T79: 2025 | U79: 2025 | V79: 2025 | W79: 2025 | X79: 2025 | Y79: 2025 | Z79: 2025 | AA79: 2025 | AB79: 2025 | AC79: 2025 | AD79: 2025 | AE79: 2025 | AF79: 2025 | AG79: 2025 | AH79: 2025

Sheet Sheet1
F1: Indicator | G1: Definition / Explanation
E2: Current Electricity Access Rate (%) | F2: Current Electricity Access Rate (%) | G2: Percentage of the total population that currently has access to electricity through grid or off-grid solutions.
E3: Current Urban Electricity Access Rate (%) | F3: Current Urban Electricity Access Rate (%) | G3: Share of the urban population with access to electricity.
E4: Current Rural Electricity Access Rate (%) | F4: Current Rural Electricity Access Rate (%) | G4: Share of the rural population with access to electricity.
E5: Target Electricity Access Rate by 2030 (%) | F5: Target Electricity Access Rate by 2030 (%) | G5: Percentage of the population targeted to have electricity access by 2030.
E6: Target Urban Electricity Access Rate by 2030 (%) | F6: Target Urban Electricity Access Rate by 2030 (%) | G6: Electricity access rate targeted for urban areas by 2030.
E7: Target Rural Electricity Access Rate by 2030 (%) | F7: Target Rural Electricity Access Rate by 2030 (%) | G7: Electricity access rate targeted for rural areas by 2030.
E8: Population Without Electricity (people) | F8: Population Without Electricity (people) | G8: Number of people currently living without electricity access.
E9: Installed Capacity – Current (MW) | F9: Installed Capacity – Current (MW) | G9: Total electricity generation capacity currently installed and operational.
E10: Installed Capacity – 2030 Target (MW) | F10: Installed Capacity – 2030 Target (MW) | G10: Total generation capacity planned to be installed by 2030.
E11: New Generation Required (MW) | F11: New Generation Required (MW) | G11: Additional generation capacity required to meet future demand and access targets.
E12: Renewable Capacity – Current (MW) | F12: Renewable Capacity – Current (MW) | G12: Installed electricity generation capacity from renewable energy sources.
E13: Renewable Capacity – 2030 Target (MW) | F13: Renewable Capacity – 2030 Target (MW) | G13: Renewable energy generation capacity targeted by 2030.
... E78: 2030 Projected population (million) | F78: 2030 Projected Population (million) | G78: Projected total population in 2030 based on demographic forecasts.

Sheet Derived_Data_Quantitative
A1: Category | B1: Indicator | C1: Benin | D1: Botswana | E1: Burundi | F1: Cameroon | G1: Chad | H1: Comoros | I1: Côte d’Ivoire | J1: DRC | K1: Ethiopia | L1: Gambia | M1: Ghana | N1: Guinea | O1: Kenya | P1: Lesotho | Q1: Liberia | R1: Madagascar | S1: Malawi | T1: Mauritania | U1: Mozambique | V1: Namibia | W1: Niger | X1: Nigeria | Y1: Republic of Congo | Z1: São Tomé & Príncipe | AA1: Senegal | AB1: Sierra Leone | AC1: Togo | AD1: Tanzania | AE1: Zambia | AF1: Zimbabwe
A2: Electricity Access | B2: Current electricity access gap (million) | C2: =Raw_Data_Quantitative!D66*(1-Raw_Data_Quantitative!D2/100) -> 8.323 | D2: =Raw_Data_Quantitative!E66*(1-Raw_Data_Quantitative!E2/100) -> 0.585 | E2: =Raw_Data_Quantitative!F66*(1-Raw_Data_Quantitative!F2/100) -> 10.374 | F2: =Raw_Data_Quantitative!G66*(1-Raw_Data_Quantitative!G2/100) -> 7.566 | G2: =Raw_Data_Quantitative!H66*(1-Raw_Data_Quantitative!H2/100) -> 18.067 | H2: =Raw_Data_Quantitative!I66*(1-Raw_Data_Quantitative!I2/100) -> 0.9 | I2: =Raw_Data_Quantitative!J66*(1-Raw_Data_Quantitative!J2/100) -> 11.484 | J2: =Raw_Data_Quantitative!K66*(1-Raw_Data_Quantitative!K2/100) -> 85.8005 | ... AF2: =Raw_Data_Quantitative!AG66*(1-Raw_Data_Quantitative!AG2/100) -> 6.308 | AG2: =SUM(C2:AF2) -> 460.20822
B3: 2030 electricity access gap (million) | C3: =IF(Raw_Data_Quantitative!D5 = 0, C2, Raw_Data_Quantitative!D67*(1-Raw_Data_Quantitative!D5/100)) -> 4.9856466 | D3: =IF(Raw_Data_Quantitative!E5 = 0, D2, Raw_Data_Quantitative!E67*(1-Raw_Data_Quantitative!E5/100)) -> 0 | E3: =IF(Raw_Data_Quantitative!F5 = 0, E2, Raw_Data_Quantitative!F67*(1-Raw_Data_Quantitative!F5/100)) -> 4.854605 | F3: =IF(Raw_Data_Quantitative!G5 = 0, F2, Raw_Data_Quantitative!G67*(1-Raw_Data_Quantitative!G5/100)) -> 0 | G3: =IF(Raw_Data_Quantitative!H5 = 0, G2, Raw_Data_Quantitative!H67*(1-Raw_Data_Quantitative!H5/100)) -> 2.4207479 | H3: =IF(Raw_Data_Quantitative!I5 = 0, H2, Raw_Data_Quantitative!I67*(1-Raw_Data_Quantitative!I5/100)) -> 0 | I3: =IF(Raw_Data_Quantitative!J5 = 0, I2, Raw_Data_Quantitative!J67*(1-Raw_Data_Quantitative!J5/100)) -> 0 | J3: =IF(Raw_Data_Quantitative!K5 = 0, J2, Raw_Data_Quantitative!K67*(1-Raw_Data_Quantitative!K5/100)) -> 49.982236 | ... AF3: =IF(Raw_Data_Quantitative!AG5 = 0, AF2, Raw_Data_Quantitative!AG67*(1-Raw_Data_Quantitative!AG5/100)) -> 0 | AG3: =SUM(C3:AF3) -> 134.53068
B4: Electricity access gap reduction, 2024-2030 (million) | C4: =C2-C3 -> 3.3373534 | D4: =D2-D3 -> 0.585 | E4: =E2-E3 -> 5.519395 | F4: =F2-F3 -> 7.566 | G4: =G2-G3 -> 15.646252 | H4: =H2-H3 -> 0.9 | I4: =I2-I3 -> 11.484 | J4: =J2-J3 -> 35.818264 | ... AF4: =AF2-AF3 -> 6.308 | AG4: =SUM(C4:AF4) -> 325.67754
B5: Electricity access population increase, 2024-2030 (million) | C5: =(Raw_Data_Quantitative!D67*(Raw_Data_Quantitative!D5/100))-(Raw_Data_Quantitative!D66*(Raw_Data_Quantitative!D2/100)) -> 5.4561754 | D5: =(Raw_Data_Quantitative!E67*(Raw_Data_Quantitative!E5/100))-(Raw_Data_Quantitative!E66*(Raw_Data_Quantitative!E2/100)) -> 0.8509175 | E5: =(Raw_Data_Quantitative!F67*(Raw_Data_Quantitative!F5/100))-(Raw_Data_Quantitative!F66*(Raw_Data_Quantitative!F2/100)) -> 7.7014115 | F5: =(Raw_Data_Quantitative!G67*(Raw_Data_Quantitative!G5/100))-(Raw_Data_Quantitative!G66*(Raw_Data_Quantitative!G2/100)) -> 12.243189 | G5: =(Raw_Data_Quantitative!H67*(Raw_Data_Quantitative!H5/100))-(Raw_Data_Quantitative!H66*(Raw_Data_Quantitative!H2/100)) -> 19.553731 | H5: =(Raw_Data_Quantitative!I67*(Raw_Data_Quantitative!I5/100))-(Raw_Data_Quantitative!I66*(Raw_Data_Quantitative!I2/100)) -> 0.9642645 | I5: =(Raw_Data_Quantitative!J67*(Raw_Data_Quantitative!J5/100))-(Raw_Data_Quantitative!J66*(Raw_Data_Quantitative!J2/100)) -> 16.283009 | J5: =(Raw_Data_Quantitative!K67*(Raw_Data_Quantitative!K5/100))-(Raw_Data_Quantitative!K66*(Raw_Data_Quantitative!K2/100)) -> 58.050465 | ... AF5: =(Raw_Data_Quantitative!AG67*(Raw_Data_Quantitative!AG5/100))-(Raw_Data_Quantitative!AG66*(Raw_Data_Quantitative!AG2/100)) -> 8.3183485 | AG5: =SUM(C5:AF5) -> 475.49952
A6: Clean Cooking Access | B6: Current clean cooking access gap (million) | C6: =Raw_Data_Quantitative!D66*(1-Raw_Data_Quantitative!D50/100) -> 12.9775 | D6: =Raw_Data_Quantitative!E66*(1-Raw_Data_Quantitative!E50/100) -> 0.835 | E6: =Raw_Data_Quantitative!F66*(1-Raw_Data_Quantitative!F50/100) -> 14 | F6: =Raw_Data_Quantitative!G66*(1-Raw_Data_Quantitative!G50/100) -> 22.2906 | G6: =Raw_Data_Quantitative!H66*(1-Raw_Data_Quantitative!H50/100) -> 20.3 | H6: =Raw_Data_Quantitative!I66*(1-Raw_Data_Quantitative!I50/100) -> 0.8955 | I6: =Raw_Data_Quantitative!J66*(1-Raw_Data_Quantitative!J50/100) -> 25.52 | J6: =Raw_Data_Quantitative!K66*(1-Raw_Data_Quantitative!K50/100) -> 103.835 | ... AF6: =Raw_Data_Quantitative!AG66*(1-Raw_Data_Quantitative!AG50/100) -> 10.1924 | AG6: =SUM(C6:AF6) -> 809.452
B7: 2030 clean cooking access gap (million) | C7: =IF(Raw_Data_Quantitative!D58=0,C6,Raw_Data_Quantitative!D67*(1-Raw_Data_Quantitative!D58/100)) -> 8.309411 | D7: =IF(Raw_Data_Quantitative!E58=0,D6,Raw_Data_Quantitative!E67*(1-Raw_Data_Quantitative!E58/100)) -> 0.27659175 | E7: =IF(Raw_Data_Quantitative!F58=0,E6,Raw_Data_Quantitative!F67*(1-Raw_Data_Quantitative!F58/100)) -> 9.7092099 | F7: =IF(Raw_Data_Quantitative!G58=0,F6,Raw_Data_Quantitative!G67*(1-Raw_Data_Quantitative!G58/100)) -> 20.266314 | G7: =IF(Raw_Data_Quantitative!H58=0,G6,Raw_Data_Quantitative!H67*(1-Raw_Data_Quantitative!H58/100)) -> 13.072039 | H7: =IF(Raw_Data_Quantitative!I58=0,H6,Raw_Data_Quantitative!I67*(1-Raw_Data_Quantitative!I58/100)) -> 0.67498515 | I7: =IF(Raw_Data_Quantitative!J58=0,I6,Raw_Data_Quantitative!J67*(1-Raw_Data_Quantitative!J58/100)) -> 18.349504 | J7: =IF(Raw_Data_Quantitative!K58=0,J6,Raw_Data_Quantitative!K67*(1-Raw_Data_Quantitative!K58/100)) -> 92.072541 | ... AF7: =IF(Raw_Data_Quantitative!AG58=0,AF6,Raw_Data_Quantitative!AG67*(1-Raw_Data_Quantitative!AG58/100)) -> 5.5831046 | AG7: =SUM(C7:AF7) -> 411.04683
B8: Clean cooking access gap reduction, 2024-2030 (million) | C8: =C6-C7 -> 4.668089 | D8: =D6-D7 -> 0.55840825 | E8: =E6-E7 -> 4.2907901 | F8: =F6-F7 -> 2.0242863 | G8: =G6-G7 -> 7.2279613 | H8: =H6-H7 -> 0.22051485 | I8: =I6-I7 -> 7.1704955 | J8: =J6-J7 -> 11.762459 | ... AF8: =AF6-AF7 -> 4.6092955 | AG8: =SUM(C8:AF8) -> 398.40517
B9: Clean cooking population increase, 2024-2030 (million) | C9: =(Raw_Data_Quantitative!D67*(Raw_Data_Quantitative!D58/100))-(Raw_Data_Quantitative!D66*(Raw_Data_Quantitative!D50/100)) -> 6.786911 | D9: =(Raw_Data_Quantitative!E67*(Raw_Data_Quantitative!E58/100))-(Raw_Data_Quantitative!E66*(Raw_Data_Quantitative!E50/100)) -> 0.82432575 | E9: =(Raw_Data_Quantitative!F67*(Raw_Data_Quantitative!F58/100))-(Raw_Data_Quantitative!F66*(Raw_Data_Quantitative!F50/100)) -> 6.4728066 | F9: =(Raw_Data_Quantitative!G67*(Raw_Data_Quantitative!G58/100))-(Raw_Data_Quantitative!G66*(Raw_Data_Quantitative!G50/100)) -> 6.7014758 | G9: =(Raw_Data_Quantitative!H67*(Raw_Data_Quantitative!H58/100))-(Raw_Data_Quantitative!H66*(Raw_Data_Quantitative!H50/100)) -> 11.13544 | H9: =(Raw_Data_Quantitative!I67*(Raw_Data_Quantitative!I58/100))-(Raw_Data_Quantitative!I66*(Raw_Data_Quantitative!I50/100)) -> 0.28477935 | I9: =(Raw_Data_Quantitative!J67*(Raw_Data_Quantitative!J58/100))-(Raw_Data_Quantitative!J66*(Raw_Data_Quantitative!J50/100)) -> 11.969504 | J9: =(Raw_Data_Quantitative!K67*(Raw_Data_Quantitative!K58/100))-(Raw_Data_Quantitative!K66*(Raw_Data_Quantitative!K50/100)) -> 33.99466 | ... AF9: =(Raw_Data_Quantitative!AG67*(Raw_Data_Quantitative!AG58/100))-(Raw_Data_Quantitative!AG66*(Raw_Data_Quantitative!AG50/100)) -> 6.6196439 | AG9: =SUM(C9:AF9) -> 541.08234
B10: USD per Unserved Person
B11: MW per Million People
B12: Investment per MW Installed (USD/MW)
B13: Access Gap (% to Universal)
B14: Renewable Share Increase (% points)

Sheet Copy of Derived_Data_Quantitati
A1: Category | B1: Indicator | D1: Benin | E1: Botswana | F1: Burundi | G1: Cameroon | H1: Chad | I1: Comoros | J1: Côte d’Ivoire | K1: DRC | L1: Ethiopia | M1: Gambia | N1: Ghana | O1: Guinea | P1: Kenya | Q1: Lesotho | R1: Liberia | S1: Madagascar | T1: Malawi | U1: Mauritania | V1: Mozambique | W1: Namibia | X1: Niger | Y1: Nigeria | Z1: Republic of Congo | AA1: São Tomé & Príncipe | AB1: Senegal | AC1: Sierra Leone | AD1: Togo | AE1: Tanzania | AF1: Zambia | AG1: Zimbabwe
A2: Electricity Access | B2: Current electricity access gap (million) | D2: =Raw_Data_Quantitative!D66*(1-Raw_Data_Quantitative!D2/100) -> 8.323 | E2: =Raw_Data_Quantitative!E66*(1-Raw_Data_Quantitative!E2/100) -> 0.585 | F2: =Raw_Data_Quantitative!F66*(1-Raw_Data_Quantitative!F2/100) -> 10.374 | G2: =Raw_Data_Quantitative!G66*(1-Raw_Data_Quantitative!G2/100) -> 7.566 | H2: =Raw_Data_Quantitative!H66*(1-Raw_Data_Quantitative!H2/100) -> 18.067 | I2: =Raw_Data_Quantitative!I66*(1-Raw_Data_Quantitative!I2/100) -> 0.9 | J2: =Raw_Data_Quantitative!J66*(1-Raw_Data_Quantitative!J2/100) -> 11.484 | K2: =Raw_Data_Quantitative!K66*(1-Raw_Data_Quantitative!K2/100) -> 85.8005 | ... AG2: =Raw_Data_Quantitative!AG66*(1-Raw_Data_Quantitative!AG2/100) -> 6.308 | AH2: =SUM(D2:AG2) -> 460.20822
B3: 2030 electricity access gap (million) | D3: =IF(Raw_Data_Quantitative!D5 = 0, D2, Raw_Data_Quantitative!D67*(1-Raw_Data_Quantitative!D5/100)) -> 4.9856466 | E3: =IF(Raw_Data_Quantitative!E5 = 0, E2, Raw_Data_Quantitative!E67*(1-Raw_Data_Quantitative!E5/100)) -> 0 | F3: =IF(Raw_Data_Quantitative!F5 = 0, F2, Raw_Data_Quantitative!F67*(1-Raw_Data_Quantitative!F5/100)) -> 4.854605 | G3: =IF(Raw_Data_Quantitative!G5 = 0, G2, Raw_Data_Quantitative!G67*(1-Raw_Data_Quantitative!G5/100)) -> 0 | H3: =IF(Raw_Data_Quantitative!H5 = 0, H2, Raw_Data_Quantitative!H67*(1-Raw_Data_Quantitative!H5/100)) -> 2.4207479 | I3: =IF(Raw_Data_Quantitative!I5 = 0, I2, Raw_Data_Quantitative!I67*(1-Raw_Data_Quantitative!I5/100)) -> 0 | J3: =IF(Raw_Data_Quantitative!J5 = 0, J2, Raw_Data_Quantitative!J67*(1-Raw_Data_Quantitative!J5/100)) -> 0 | K3: =IF(Raw_Data_Quantitative!K5 = 0, K2, Raw_Data_Quantitative!K67*(1-Raw_Data_Quantitative!K5/100)) -> 49.982236 | ... AG3: =IF(Raw_Data_Quantitative!AG5 = 0, AG2, Raw_Data_Quantitative!AG67*(1-Raw_Data_Quantitative!AG5/100)) -> 0 | AH3: =SUM(D3:AG3) -> 134.53068
B4: Electricity access gap reduction, 2024-2030 (million) | D4: =D2-D3 -> 3.3373534 | E4: =E2-E3 -> 0.585 | F4: =F2-F3 -> 5.519395 | G4: =G2-G3 -> 7.566 | H4: =H2-H3 -> 15.646252 | I4: =I2-I3 -> 0.9 | J4: =J2-J3 -> 11.484 | K4: =K2-K3 -> 35.818264 | ... AG4: =AG2-AG3 -> 6.308 | AH4: =SUM(D4:AG4) -> 325.67754
B5: Electricity access population increase, 2024-2030 (million) | D5: =(Raw_Data_Quantitative!D67*(Raw_Data_Quantitative!D5/100))-(Raw_Data_Quantitative!D66*(Raw_Data_Quantitative!D2/100)) -> 5.4561754 | E5: =(Raw_Data_Quantitative!E67*(Raw_Data_Quantitative!E5/100))-(Raw_Data_Quantitative!E66*(Raw_Data_Quantitative!E2/100)) -> 0.8509175 | F5: =(Raw_Data_Quantitative!F67*(Raw_Data_Quantitative!F5/100))-(Raw_Data_Quantitative!F66*(Raw_Data_Quantitative!F2/100)) -> 7.7014115 | G5: =(Raw_Data_Quantitative!G67*(Raw_Data_Quantitative!G5/100))-(Raw_Data_Quantitative!G66*(Raw_Data_Quantitative!G2/100)) -> 12.243189 | H5: =(Raw_Data_Quantitative!H67*(Raw_Data_Quantitative!H5/100))-(Raw_Data_Quantitative!H66*(Raw_Data_Quantitative!H2/100)) -> 19.553731 | I5: =(Raw_Data_Quantitative!I67*(Raw_Data_Quantitative!I5/100))-(Raw_Data_Quantitative!I66*(Raw_Data_Quantitative!I2/100)) -> 0.9642645 | J5: =(Raw_Data_Quantitative!J67*(Raw_Data_Quantitative!J5/100))-(Raw_Data_Quantitative!J66*(Raw_Data_Quantitative!J2/100)) -> 16.283009 | K5: =(Raw_Data_Quantitative!K67*(Raw_Data_Quantitative!K5/100))-(Raw_Data_Quantitative!K66*(Raw_Data_Quantitative!K2/100)) -> 58.050465 | ... AG5: =(Raw_Data_Quantitative!AG67*(Raw_Data_Quantitative!AG5/100))-(Raw_Data_Quantitative!AG66*(Raw_Data_Quantitative!AG2/100)) -> 8.3183485 | AH5: =SUM(D5:AG5) -> 475.49952
A6: Clean Cooking Access | B6: Current clean cooking access gap (million) | D6: =Raw_Data_Quantitative!D66*(1-Raw_Data_Quantitative!D50/100) -> 12.9775 | E6: =Raw_Data_Quantitative!E66*(1-Raw_Data_Quantitative!E50/100) -> 0.835 | F6: =Raw_Data_Quantitative!F66*(1-Raw_Data_Quantitative!F50/100) -> 14 | G6: =Raw_Data_Quantitative!G66*(1-Raw_Data_Quantitative!G50/100) -> 22.2906 | H6: =Raw_Data_Quantitative!H66*(1-Raw_Data_Quantitative!H50/100) -> 20.3 | I6: =Raw_Data_Quantitative!I66*(1-Raw_Data_Quantitative!I50/100) -> 0.8955 | J6: =Raw_Data_Quantitative!J66*(1-Raw_Data_Quantitative!J50/100) -> 25.52 | K6: =Raw_Data_Quantitative!K66*(1-Raw_Data_Quantitative!K50/100) -> 103.835 | ... AG6: =Raw_Data_Quantitative!AG66*(1-Raw_Data_Quantitative!AG50/100) -> 10.1924 | AH6: =SUM(D6:AG6) -> 809.452
B7: 2030 clean cooking access gap (million) | D7: =IF(Raw_Data_Quantitative!D58=0,D6,Raw_Data_Quantitative!D67*(1-Raw_Data_Quantitative!D58/100)) -> 8.309411 | E7: =IF(Raw_Data_Quantitative!E58=0,E6,Raw_Data_Quantitative!E67*(1-Raw_Data_Quantitative!E58/100)) -> 0.27659175 | F7: =IF(Raw_Data_Quantitative!F58=0,F6,Raw_Data_Quantitative!F67*(1-Raw_Data_Quantitative!F58/100)) -> 9.7092099 | G7: =IF(Raw_Data_Quantitative!G58=0,G6,Raw_Data_Quantitative!G67*(1-Raw_Data_Quantitative!G58/100)) -> 20.266314 | H7: =IF(Raw_Data_Quantitative!H58=0,H6,Raw_Data_Quantitative!H67*(1-Raw_Data_Quantitative!H58/100)) -> 13.072039 | I7: =IF(Raw_Data_Quantitative!I58=0,I6,Raw_Data_Quantitative!I67*(1-Raw_Data_Quantitative!I58/100)) -> 0.67498515 | J7: =IF(Raw_Data_Quantitative!J58=0,J6,Raw_Data_Quantitative!J67*(1-Raw_Data_Quantitative!J58/100)) -> 18.349504 | K7: =IF(Raw_Data_Quantitative!K58=0,K6,Raw_Data_Quantitative!K67*(1-Raw_Data_Quantitative!K58/100)) -> 92.072541 | ... AG7: =IF(Raw_Data_Quantitative!AG58=0,AG6,Raw_Data_Quantitative!AG67*(1-Raw_Data_Quantitative!AG58/100)) -> 5.5831046 | AH7: =SUM(D7:AG7) -> 411.04683
B8: Clean cooking access gap reduction, 2024-2030 (million) | D8: =D6-D7 -> 4.668089 | E8: =E6-E7 -> 0.55840825 | F8: =F6-F7 -> 4.2907901 | G8: =G6-G7 -> 2.0242863 | H8: =H6-H7 -> 7.2279613 | I8: =I6-I7 -> 0.22051485 | J8: =J6-J7 -> 7.1704955 | K8: =K6-K7 -> 11.762459 | ... AG8: =AG6-AG7 -> 4.6092955 | AH8: =SUM(D8:AG8) -> 398.40517
B9: Clean cooking population increase, 2024-2030 (million) | D9: =(Raw_Data_Quantitative!D67*(Raw_Data_Quantitative!D58/100))-(Raw_Data_Quantitative!D66*(Raw_Data_Quantitative!D50/100)) -> 6.786911 | E9: =(Raw_Data_Quantitative!E67*(Raw_Data_Quantitative!E58/100))-(Raw_Data_Quantitative!E66*(Raw_Data_Quantitative!E50/100)) -> 0.82432575 | F9: =(Raw_Data_Quantitative!F67*(Raw_Data_Quantitative!F58/100))-(Raw_Data_Quantitative!F66*(Raw_Data_Quantitative!F50/100)) -> 6.4728066 | G9: =(Raw_Data_Quantitative!G67*(Raw_Data_Quantitative!G58/100))-(Raw_Data_Quantitative!G66*(Raw_Data_Quantitative!G50/100)) -> 6.7014758 | H9: =(Raw_Data_Quantitative!H67*(Raw_Data_Quantitative!H58/100))-(Raw_Data_Quantitative!H66*(Raw_Data_Quantitative!H50/100)) -> 11.13544 | I9: =(Raw_Data_Quantitative!I67*(Raw_Data_Quantitative!I58/100))-(Raw_Data_Quantitative!I66*(Raw_Data_Quantitative!I50/100)) -> 0.28477935 | J9: =(Raw_Data_Quantitative!J67*(Raw_Data_Quantitative!J58/100))-(Raw_Data_Quantitative!J66*(Raw_Data_Quantitative!J50/100)) -> 11.969504 | K9: =(Raw_Data_Quantitative!K67*(Raw_Data_Quantitative!K58/100))-(Raw_Data_Quantitative!K66*(Raw_Data_Quantitative!K50/100)) -> 33.99466 | ... AG9: =(Raw_Data_Quantitative!AG67*(Raw_Data_Quantitative!AG58/100))-(Raw_Data_Quantitative!AG66*(Raw_Data_Quantitative!AG50/100)) -> 6.6196439 | AH9: =SUM(D9:AG9) -> 541.08234
A12: Electricity Access | B12: Current Electricity Access Rate (%) | C12: M300 National Energy Compacts | D12: 42.6 | E12: 76.6 | F12: 25.9 | G12: 74 | H12: 11 | I12: 95 | J12: 64 | K12: 21.5 | L12: 44 | M12: 73.7 | N12: 89 | O12: 53 | P12: 75 | Q12: 53 | R12: 32.7 | S12: 36 | T12: 25.9 | U12: 55 | V12: 60.1 | W12: 59.5 | X12: 20.84 | Y12: 61 | Z12: 31.66 | AA12: 84 | AB12: 84 | AC12: 36 | AD12: 70 | AE12: 78.4 | AF12: 53.6 | AG12: 62
B13: Target Electricity Access Rate by 2030 (%) | C13: M300 National Energy Compacts | D13: 70 | E13: 100 | F13: 70 | G13: 100 | H13: 90 | I13: 100 | J13: 100 | K13: 62 | L13: 75 | M13: 100 | N13: 99.8 | O13: 100 | P13: 100 | Q13: 100 | R13: 75 | S13: 80 | T13: 70 | U13: 100 | V13: 100 | W13: 70 | X13: 60 | Y13: 100 | Z13: 81.3 | AA13: 100 | AB13: 100 | AC13: 78 | AD13: 100 | AE13: 100 | AF13: 100 | AG13: 100
A14: Clean Cooking | B14: Clean cooking access - current (%) | C14: M300 National Energy Compacts | D14: 10.5 | E14: 66.6 | G14: 23.4 | I14: 0.5 | J14: 20 | K14: 5 | L14: 8 | M14: 25 | N14: 36.9 | O14: 12 | P14: 34.4 | Q14: 45.2 | R14: 0.8 | S14: 14 | T14: 24.5 | U14: 54 | V14: 17 | W14: 48.5 | X14: 6 | Y14: 26 | Z14: 39.6 | AA14: 62 | AC14: 1.5 | AD14: 14 | AE14: 6.9 | AF14: 8.9 | AG14: 38.6
B15: Clean cooking access - 2030 target (%) | C15: M300 National Energy Compacts | D15: 50 | E15: 90 | F15: 40 | G15: 40 | H15: 46 | I15: 30 | J15: 50 | K15: 30 | L15: 57.74 | M15: 50 | N15: 50 | O15: 35 | P15: 100 | Q15: 75 | S15: 50 | T15: 75 | V15: 54 | W15: 61 | X15: 12 | Y15: 100 | Z15: 81.3 | AA15: 75 | AC15: 25 | AD15: 80 | AE15: 75 | AF15: 40 | AG15: 70
A16: Population | B16: 2024 population (million) | C16: World Bank Open Database | D16: 14.5 | E16: 2.5 | F16: 14 | G16: 29.1 | H16: 20.3 | I16: 0.9 | J16: 31.9 | K16: 109.3 | L16: 132.1 | M16: 2.8 | N16: 34.4 | O16: 14.8 | P16: 56.4 | Q16: 2.3 | R16: 5.6 | S16: 32 | T16: 21.7 | U16: 5.2 | V16: 34.6 | W16: 3 | X16: 27 | Y16: 232.7 | Z16: 6.3 | AA16: 0.2 | AB16: 18.5 | AC16: 8.6 | AD16: 9.5 | AE16: 68.6 | AF16: 21.3 | AG16: 16.6
B17: 2030 Projected population (million) | C17: UN World Population Prospects | D17: 16.62 | E17: 2.77 | F17: 16.18 | G17: 33.78 | H17: 24.21 | I17: 0.96 | J17: 36.7 | K17: 131.53 | L17: 152.86 | M17: 3.13 | N17: 38.22 | O17: 16.81 | P17: 63.1 | Q17: 2.49 | R17: 6.37 | S17: 36.69 | T17: 25.16 | U17: 6.06 | V17: 40.85 | W17: 3.39 | X17: 32.52 | Y17: 262.38 | Z17: 7.28 | AA17: 0.26 | AB17: 21.16 | AC17: 9.69 | AD17: 10.79 | AE17: 80.91 | AF17: 25.02 | AG17: 18.61
A18: Generation Capacity & Supply Mix | B18: Installed Capacity – Current (MW) | C18: M300 National Energy Compacts | D18: 199.8 | E18: 892 | F18: 204.88 | G18: 3000 | H18: 487 | I18: 53 | J18: 2907 | K18: 3067 | L18: 9761 | M18: 99 | N18: 5641 | O18: 1310 | P18: 2627 | Q18: 104.7 | R18: 126 | S18: 828 | T18: 550 | U18: 615.1 | V18: 2922 | W18: 695 | X18: 352 | Y18: 12000 | Z18: 748 | AA18: 38 | AC18: 271 | AD18: 267.5 | AE18: 3404.2 | AF18: 3811.3 | AG18: 2962
B19: Installed Capacity – 2030 Target (MW) | C19: M300 National Energy Compacts | D19: 794 | E19: 950 | F19: 410 | G19: 3000 | H19: 866 | J19: 5128 | K19: 13576 | L19: 14000 | N19: 6200 | O19: 3827 | P19: 5952 | T19: 1490 | W19: 1149 | Z19: 3701 | AC19: 1120 | AD19: 1154.5 | AF19: 10000 | AG19: 5432
B20: New Generation Required (MW) | C20: M300 National Energy Compacts | H20: 866 | J20: 1374 | O20: 2517 | P20: 3325 | T20: 848 | V20: 3100 | W20: 454 | Z20: 2953 | AA20: 60 | AD20: 894 | AE20: 1973 | AF20: 6200
A21: Finance | B21: Total Investment Required (USD) | C21: M300 National Energy Compacts | D21: 2360000000 | E21: 2520000000 | F21: 3490000000 | G21: 12554000000 | H21: 1950000000 | I21: 390210000 | J21: 8460000000 | K21: 37048660000 | L21: 9646040000 | M21: 552000000 | N21: 4404000000 | O21: 8900000000 | P21: 19115000000 | Q21: 1970000000 | R21: 1500000000 | S21: 7200000000 | T21: 5500000000 | U21: 3067300000 | V21: 18620000000 | W21: 1764000000 | Y21: 32700000000 | Z21: 11543000000 | AA21: 297000000 | AB21: 6300000000 | AC21: 2245000000 | AD21: 12889999999 | AE21: 3000000000 | AF21: 11880000000 | AG21: 9134890000
B22: Public Financing Required (USD) | C22: M300 National Energy Compacts | D22: 1420000000 | E22: 1414000000 | F22: 1950000000 | H22: 1299744000 | I22: 117000000 | J22: 4620000000 | K22: 17314100000 | L22: 6584240000 | M22: 305000000 | N22: 1793000000 | O22: 1200000000 | P22: 14002000000 | Q22: 499700000 | R22: 1150000000 | S22: 2880000000 | U22: 1220260000 | V22: 9923000000 | W22: 1353000000 | Y22: 17200000000 | Z22: 3276000000 | AA22: 108000000 | AB22: 3926000000 | AC22: 835000000 | AD22: 8850000000 | AE22: 1320000000
B23: Private Financing Required (USD) | C23: M300 National Energy Compacts | D23: 940000000 | E23: 1106000000 | F23: 1540000000 | G23: 6372000000 | H23: 650256000 | I23: 273000000 | J23: 1940000000 | K23: 19734550000 | L23: 3061800000 | M23: 247000000 | N23: 2611000000 | O23: 7641000000 | P23: 5113000000 | Q23: 1470000000 | R23: 140000000 | S23: 4320000000 | T23: 162800000 | U23: 1225800000 | V23: 8698000000 | W23: 411000000 | X23: 527000000 | Y23: 15500000000 | Z23: 8267000000 | AA23: 190000000 | AB23: 2300000000 | AC23: 1410000000 | AD23: 4039000000 | AE23: 1680000000 | AF23: 9500000000 | AG23: 4420000000
B25: 2024 population with electricity access (million) | D25: =D16*(D12/100) -> 6.177 | E25: =E16*(E12/100) -> 1.915 | F25: =F16*(F12/100) -> 3.626 | G25: =G16*(G12/100) -> 21.534 | H25: =H16*(H12/100) -> 2.233 | I25: =I16*(I12/100) -> 0.855 | J25: =J16*(J12/100) -> 20.416 | K25: =K16*(K12/100) -> 23.4995 | ... AG25: =AG16*(AG12/100) -> 10.292
B26: 2030 population with electricity access (million) | D26: =D17*(D13/100) -> 11.634 | E26: =E17*(E13/100) -> 2.77 | F26: =F17*(F13/100) -> 11.326 | G26: =G17*(G13/100) -> 33.78 | H26: =H17*(H13/100) -> 21.789 | I26: =I17*(I13/100) -> 0.96 | J26: =J17*(J13/100) -> 36.7 | K26: =K17*(K13/100) -> 81.5486 | ... AG26: =AG17*(AG13/100) -> 18.61
B27: 2024 population with clean cooking access (million) | D27: =IF(ISBLANK(D14),"",D16*(D14/100)) -> 1.5225 | E27: =IF(ISBLANK(E14),"",E16*(E14/100)) -> 1.665 | F27: =IF(ISBLANK(F14),"",F16*(F14/100)) | G27: =IF(ISBLANK(G14),"",G16*(G14/100)) -> 6.8094 | H27: =IF(ISBLANK(H14),"",H16*(H14/100)) | I27: =IF(ISBLANK(I14),"",I16*(I14/100)) -> 0.0045 | J27: =IF(ISBLANK(J14),"",J16*(J14/100)) -> 6.38 | K27: =IF(ISBLANK(K14),"",K16*(K14/100)) -> 5.465 | ... AG27: =IF(ISBLANK(AG14),"",AG16*(AG14/100)) -> 6.4076
B28: 2030 population with clean cooking access (million) | D28: =IF(ISBLANK(D15),D17*(D14/100),D17*(D15/100)) -> 8.31 | E28: =IF(ISBLANK(E15),E17*(E14/100),E17*(E15/100)) -> 2.493 | F28: =IF(ISBLANK(F15),F17*(F14/100),F17*(F15/100)) -> 6.472 | G28: =IF(ISBLANK(G15),G17*(G14/100),G17*(G15/100)) -> 13.512 | H28: =IF(ISBLANK(H15),H17*(H14/100),H17*(H15/100)) -> 11.1366 | I28: =IF(ISBLANK(I15),I17*(I14/100),I17*(I15/100)) -> 0.288 | J28: =IF(ISBLANK(J15),J17*(J14/100),J17*(J15/100)) -> 18.35 | K28: =IF(ISBLANK(K15),K17*(K14/100),K17*(K15/100)) -> 39.459 | ... AG28: =IF(ISBLANK(AG15),AG17*(AG14/100),AG17*(AG15/100)) -> 13.027
B29: Electricity access population increase, 2024-2030 (million) | D29: =D26-D25 -> 5.457 | E29: =E26-E25 -> 0.855 | F29: =F26-F25 -> 7.7 | G29: =G26-G25 -> 12.246 | H29: =H26-H25 -> 19.556 | I29: =I26-I25 -> 0.105 | J29: =J26-J25 -> 16.284 | K29: =K26-K25 -> 58.0491 | ... AG29: =AG26-AG25 -> 8.318 | AH29: =SUM(D29:AG29) -> 474.62272
B30: Clean cooking population increase, 2024-2030 (million) | D30: =D28-D27 -> 6.7875 | E30: =E28-E27 -> 0.828 | F30: =F28-F27 -> #VALUE! | G30: =G28-G27 -> 6.7026 | H30: =H28-H27 -> #VALUE! | I30: =I28-I27 -> 0.2835 | J30: =J28-J27 -> 11.97 | K30: =K28-K27 -> 33.994 | ... AG30: =AG28-AG27 -> 6.6194 | AH30: =SUM(D30:AG30) -> #VALUE!
B31: 2024 electricity access gap, population (million) | D31: =D16-(D16*(D12/100)) -> 8.323 | E31: =E16-(E16*(E12/100)) -> 0.585 | F31: =F16-(F16*(F12/100)) -> 10.374 | G31: =G16-(G16*(G12/100)) -> 7.566 | H31: =H16-(H16*(H12/100)) -> 18.067 | I31: =I16-(I16*(I12/100)) -> 0.045 | J31: =J16-(J16*(J12/100)) -> 11.484 | K31: =K16-(K16*(K12/100)) -> 85.8005 | ... AG31: =AG16-(AG16*(AG12/100)) -> 6.308
B32: 2030 electricity access gap, population (million) | D32: =D17-(D17*(D13/100)) -> 4.986 | E32: =E17-(E17*(E13/100)) -> 0 | F32: =F17-(F17*(F13/100)) -> 4.854 | G32: =G17-(G17*(G13/100)) -> 0 | H32: =H17-(H17*(H13/100)) -> 2.421 | I32: =I17-(I17*(I13/100)) -> 0 | J32: =J17-(J17*(J13/100)) -> 0 | K32: =K17-(K17*(K13/100)) -> 49.9814 | ... AG32: =AG17-(AG17*(AG13/100)) -> 0
B33: 2024 clean cooking access gap, population (million) | D33: =IF(ISBLANK(D14),"",(D16-D27)) -> 12.9775 | E33: =IF(ISBLANK(E14),"",(E16-E27)) -> 0.835 | F33: =IF(ISBLANK(F14),"",(F16-F27)) | G33: =IF(ISBLANK(G14),"",(G16-G27)) -> 22.2906 | H33: =IF(ISBLANK(H14),"",(H16-H27)) | I33: =IF(ISBLANK(I14),"",(I16-I27)) -> 0.8955 | J33: =IF(ISBLANK(J14),"",(J16-J27)) -> 25.52 | K33: =IF(ISBLANK(K14),"",(K16-K27)) -> 103.835 | ... AG33: =IF(ISBLANK(AG14),"",(AG16-AG27)) -> 10.1924
B34: 2030 clean cooking access gap, population (million) | D34: =IF(ISBLANK(D15),"",(D17-D28)) -> 8.31 | E34: =IF(ISBLANK(E15),"",(E17-E28)) -> 0.277 | F34: =IF(ISBLANK(F15),"",(F17-F28)) -> 9.708 | G34: =IF(ISBLANK(G15),"",(G17-G28)) -> 20.268 | H34: =IF(ISBLANK(H15),"",(H17-H28)) -> 13.0734 | I34: =IF(ISBLANK(I15),"",(I17-I28)) -> 0.672 | J34: =IF(ISBLANK(J15),"",(J17-J28)) -> 18.35 | K34: =IF(ISBLANK(K15),"",(K17-K28)) -> 92.071 | ... AG34: =IF(ISBLANK(AG15),"",(AG17-AG28)) -> 5.583
B35: Electricity access gap decrease, population, 2024-2030 (million) | D35: =IF(D31="","",(D31-D32)) -> 3.337 | E35: =IF(E31="","",(E31-E32)) -> 0.585 | F35: =IF(F31="","",(F31-F32)) -> 5.52 | G35: =IF(G31="","",(G31-G32)) -> 7.566 | H35: =IF(H31="","",(H31-H32)) -> 15.646 | I35: =IF(I31="","",(I31-I32)) -> 0.045 | J35: =IF(J31="","",(J31-J32)) -> 11.484 | K35: =IF(K31="","",(K31-K32)) -> 35.8191 | ... AG35: =IF(AG31="","",(AG31-AG32)) -> 6.308 | AH35: =SUM(D35:AG35) -> 324.82272
B36: Clean cooking access gap decrease, population, 2024-2030 (million) | D36: =IF(D33="","",(D33-D34)) -> 4.6675 | E36: =IF(E33="","",(E33-E34)) -> 0.558 | F36: =IF(F33="","",(F33-F34)) | G36: =IF(G33="","",(G33-G34)) -> 2.0226 | H36: =IF(H33="","",(H33-H34)) | I36: =IF(I33="","",(I33-I34)) -> 0.2235 | J36: =IF(J33="","",(J33-J34)) -> 7.17 | K36: =IF(K33="","",(K33-K34)) -> 11.764 | ... AG36: =IF(AG33="","",(AG33-AG34)) -> 4.6094 | AH36: =SUM(D36:AG36) -> #VALUE!
B38: Investment per MW, investment intensity (USD/MW) | D38: =IF(ISBLANK(D20),"",(D21/D20)) | E38: =IF(ISBLANK(E20),"",(E21/E20)) | F38: =IF(ISBLANK(F20),"",(F21/F20)) | G38: =IF(ISBLANK(G20),"",(G21/G20)) | H38: =IF(ISBLANK(H20),"",(H21/H20)) -> 2251732.1 | I38: =IF(ISBLANK(I20),"",(I21/I20)) | J38: =IF(ISBLANK(J20),"",(J21/J20)) -> 6157205.2 | K38: =IF(ISBLANK(K20),"",(K21/K20)) | ... AG38: =IF(ISBLANK(AG20),"",(AG21/AG20))
B39: MW per investment, investment efficiency (MW/USD) | D39: =IF(ISBLANK(D20),"",(D20/D21)) | E39: =IF(ISBLANK(E20),"",(E20/E21)) | F39: =IF(ISBLANK(F20),"",(F20/F21)) | G39: =IF(ISBLANK(G20),"",(G20/G21)) | H39: =IF(ISBLANK(H20),"",(H20/H21)) -> 4.4410256e-07 | I39: =IF(ISBLANK(I20),"",(I20/I21)) | J39: =IF(ISBLANK(J20),"",(J20/J21)) -> 1.6241135e-07 | K39: =IF(ISBLANK(K20),"",(K20/K21)) | ... AG39: =IF(ISBLANK(AG20),"",(AG20/AG21))
B40: MW per investment, investment efficiency (MW/USD billion) | D40: =IF(ISBLANK(D20),"",(D20/D21)*1000000000) | E40: =IF(ISBLANK(E20),"",(E20/E21)*1000000000) | F40: =IF(ISBLANK(F20),"",(F20/F21)*1000000000) | G40: =IF(ISBLANK(G20),"",(G20/G21)*1000000000) | H40: =IF(ISBLANK(H20),"",(H20/H21)*1000000000) -> 444.10256 | I40: =IF(ISBLANK(I20),"",(I20/I21)*1000000000) | J40: =IF(ISBLANK(J20),"",(J20/J21)*1000000000) -> 162.41135 | K40: =IF(ISBLANK(K20),"",(K20/K21)*1000000000) | ... AG40: =IF(ISBLANK(AG20),"",(AG20/AG21)*1000000000)
A42: Row 29 | B42: Current electricity access gap (million)
A43: Row 30 | B43: 2030 electricity access gap (million)
A44: Row 35 | B44: Electricity access gap reduction, 2024-2030 (million)
A45: Row 26 | B45: Electricity access population increase, 2024-2030 (million)
A46: Row 29 | B46: Current clean cooking access gap (million)
A47: Row 30 | B47: 2030 clean cooking access gap (million)
A48: Row 36 | B48: Clean cooking access gap reduction, 2024-2030 (million)
A49: Row 27 | B49: Clean cooking population increase, 2024-2030 (million)

Sheet Raw_Data_Quantitative
A1: Category | B1: Indicator | C1: Data Source | D1: Benin | E1: Botswana | F1: Burundi | G1: Cameroon | H1: Chad | I1: Comoros | J1: Côte d’Ivoire | K1: Democratic Republic of Congo | L1: Ethiopia | M1: Gambia | N1: Ghana | O1: Guinea | P1: Kenya | Q1: Lesotho | R1: Liberia | S1: Madagascar | T1: Malawi | U1: Mauritania | V1: Mozambique | W1: Namibia | X1: Niger | Y1: Nigeria | Z1: Republic of Congo | AA1: São Tomé & Príncipe | AB1: Senegal | AC1: Sierra Leone | AD1: Togo | AE1: Tanzania | AF1: Zambia | AG1: Zimbabwe
A2: Electricity Access | B2: Current Electricity Access Rate (%) | C2: M300 National Energy Compacts | D2: 42.6 | E2: 76.6 | F2: 25.9 | G2: 74 | H2: 11 | J2: 64 | K2: 21.5 | L2: 44 | M2: 73.7 | N2: 89 | O2: 53 | P2: 75 | Q2: 53 | R2: 32.7 | S2: 36 | T2: 25.9 | U2: 55 | V2: 60.1 | W2: 59.5 | X2: 20.84 | Y2: 61 | Z2: 31.66 | AA2: 84 | AB2: 84 | AC2: 36 | AD2: 70 | AE2: 78.4 | AF2: 53.6 | AG2: 62
B3: Current Urban Electricity Access Rate (%) | C3: M300 National Energy Compacts | D3: 71.2 | F3: 66.3 | G3: 94 | H3: 20 | O3: 89 | Q3: 71.3 | S3: 72 | T3: 56.5 | U3: 91 | W3: 77.1 | Z3: 38.67 | AB3: 97.1 | AE3: 99.6 | AF3: 80.3 | AG3: 83
B4: Current Rural Electricity Access Rate (%) | C4: M300 National Energy Compacts | D4: 13.1 | F4: 17.6 | G4: 25 | H4: 1 | O4: 21 | Q4: 11.4 | S4: 11 | T4: 3.8 | U4: 6 | W4: 13.8 | X4: 5.3 | Z4: 1.01 | AB4: 64.5 | AE4: 69.6 | AF4: 34.9 | AG4: 27
B5: Target Electricity Access Rate by 2030 (%) | C5: M300 National Energy Compacts | D5: 70 | E5: 100 | F5: 70 | G5: 100 | H5: 90 | I5: 100 | J5: 100 | K5: 62 | L5: 75 | M5: 100 | N5: 99.8 | O5: 100 | P5: 100 | Q5: 100 | R5: 75 | S5: 80 | T5: 70 | U5: 100 | V5: 100 | W5: 70 | X5: 60 | Y5: 100 | Z5: 81.3 | AA5: 100 | AB5: 100 | AC5: 78 | AD5: 100 | AE5: 100 | AF5: 100 | AG5: 100
B6: Target Urban Electricity Access Rate by 2030 (%) | C6: M300 National Energy Compacts | H6: 50 | Z6: 90
B7: Target Rural Electricity Access Rate by 2030 (%) | C7: M300 National Energy Compacts | H7: 40 | Z7: 50
B8: Population Without Electricity (people) | C8: M300 National Energy Compacts | F8: 11600000 | H8: 14000000 | K8: 60000000 | M8: 633000 | N8: 3700000 | O8: 7750000 | S8: 19000000 | U8: 3400000 | Y8: 86000000 | AB8: 2800000
A9: Generation Capacity & Supply Mix | B9: Installed Capacity – Current (MW) | C9: M300 National Energy Compacts | D9: 199.8 | E9: 892 | F9: 204.88 | H9: 487 | I9: 53 | J9: 2907 | K9: 3067 | L9: 9761 | M9: 99 | N9: 5641 | O9: 1310 | Q9: 104.7 | R9: 126 | S9: 828 | T9: 550 | U9: 615.1 | V9: 2922 | W9: 695 | X9: 352 | Z9: 748 | AA9: 38 | AC9: 271 | AD9: 267.5 | AE9: 3404.2 | AF9: 3811.3 | AG9: 2962
B10: Installed Capacity – 2030 Target (MW) | C10: M300 National Energy Compacts | D10: 794 | E10: 950 | F10: 410 | G10: 3000 | H10: 866 | J10: 5128 | K10: 13576 | L10: 14000 | N10: 6200 | O10: 3827 | P10: 5952 | T10: 1490 | W10: 1149 | Z10: 3701 | AC10: 1120 | AD10: 1154.5 | AF10: 10000 | AG10: 5432
B11: New Generation Required (MW) | C11: M300 National Energy Compacts | H11: 866 | J11: 1374 | O11: 2517 | T11: 848 | V11: 3100 | W11: 454 | Z11: 2953 | AA11: 60 | AD11: 894 | AE11: 1973 | AF11: 6200 | AH11: =COUNT(D11:AG11) -> 11
B12: Renewable Capacity – Current (MW) | C12: M300 National Energy Compacts | D12: 62.3 | E12: 74.6 | G12: 36.53 | I12: =13+0.712 -> 13.712 | J12: 909 | N12: 60.8 | V12: =2193+98 -> 2291 | W12: 498.5 | Z12: 214 | AB12: 460 | AD12: 102.5 | AE12: 2011.27 | AF12: 3336 | AG12: 1282
B13: Renewable Capacity – 2030 Target (MW) | C13: M300 National Energy Compacts | D13: 417 | E13: 475 | H13: 520 | J13: 2283 | V13: =4344+303+245 -> 4892 | W13: 952.5 | Z13: 2697 | AD13: 728.5 | AF13: 9000 | AG13: 2640
B14: Solar Capacity Target (MW) | C14: M300 National Energy Compacts | E14: 1500 | G14: 150 | H14: 520 | J14: 399 | K14: 4000 | L14: 1175 | M14: 150 | N14: 850 | O14: 1086 | P14: 807 | R14: 172 | S14: 560 | V14: 303 | W14: 466.5 | AA14: 30 MWp | AC14: 392 | AD14: 569 | AE14: 463 | AF14: 3000
B15: Wind Capacity Target (MW) | C15: M300 National Energy Compacts | E15: 100 | L15: 1102 | N15: 200 | P15: 966 | Q15: 60 | V15: 245 | W15: 99 | X15: 250 | AE15: 500 | AF15: 1192
B16: Hydro Capacity Target (MW) | C16: M300 National Energy Compacts | J16: 829 | L16: 1800 | N16: 150 | O16: 791 | P16: 1403 | R16: 150 | V16: 4344 | W16: 347 | X16: 128 | AA16: 9 | AC16: 194 | AD16: 57 | AE16: 880
B17: Gas Capacity Target (MW) | C17: M300 National Energy Compacts | M17: 80 | U17: 225 | V17: 1004 | X17: 240 | Z17: 470 | AA17: 10 | AB17: 2200 | AD17: 250
B18: Battery Storage Target (MWh) | C18: M300 National Energy Compacts | M18: 40 | P18: 400 | Q18: 600 | R18: 5 | U18: 30 | W18: 96 | X18: 20 | AD18: 156
A19: Demand | B19: Peak Demand – Current (MW) | C19: M300 National Energy Compacts | E19: 678 | I19: 26.2 | Q19: 209 | R19: 108 | W19: 673 | AE19: 1888.72 | AF19: 2500 | AG19: 2000
B20: Peak Demand – 2030 (MW) | C20: M300 National Energy Compacts | T20: 774
A21: Networks & Losses | B21: Transmission Lines – Existing (km) | C21: M300 National Energy Compacts | D21: 1449.1 | E21: 4000 | F21: 650 | H21: 996 | J21: 7553 | L21: 20390 | N21: 6472.2 | O21: 1600 | P21: 9484 | T21: 2650 | U21: 1950 | V21: 5679 | X21: 1428.8 | Y21: =5530+6800 -> 12330 | Z21: =1256+500 -> 1756 | AA21: 275 | AC21: 802 | AD21: 1273 | AE21: 8025.75 | AF21: 12705
B22: Transmission Lines – Added (km) | C22: M300 National Energy Compacts | F22: 704 | H22: 400.2 | M22: 200 | O22: 352 | P22: 8000 | T22: 1940 | AC22: 1235 | AD22: 1447 | AG22: 1607
B23: Distribution Lines – Added (km) | C23: M300 National Energy Compacts | F23: 6578 | H23: 195 | P23: 212937 | Q23: 550 | T23: 22417 | AD23: 3761
B24: System Losses – Current (%) | C24: M300 National Energy Compacts | D24: 24.62 | E24: 14.35 | H24: 39 | I24: 37 | K24: 46 | L24: 27 | M24: 21 | N24: 27 | O24: 30 | P24: =4.5+11.19 -> 15.69 | R24: 45.4 | U24: 30 | V24: 24 | Y24: 42 | Z24: 45 | AA24: 34 | AC24: 50 | AD24: 16 | AE24: 14.2
B25: System Losses – Target (%) | C25: M300 National Energy Compacts | D25: 15 | H25: 15 | I25: 20 | K25: 15 | L25: 19 | M25: 18 | N25: 23 | O25: 8 | P25: =3.5+9.3 -> 12.8 | S25: 16 | AA25: 18 | AD25: 12
A26: Connections | B26: Grid Connections – New (connections) | C26: M300 National Energy Compacts | D26: 928 | E26: 220000 | F26: 1900000 | I26: 62310 | P26: 5100000 | Q26: 26400 | T26: 1150000 | V26: 4900000 | X26: 2077515 | Y26: 4700000 | Z26: 953000 | AB26: 260149 | AD26: 1300000 | AF26: 1459560 | AG26: 1200000
B27: Grid Connections – New (HH) | C27: M300 National Energy Compacts | N27: 660000 | W27: 175000 | AC27: 160000 | AE27: 8300000
B28: Off-grid Connections Target (connections) | C28: M300 National Energy Compacts | E28: 61000 | F28: 410000 | Q28: 18900 | T28: 1550000 | AD28: 133000 | AF28: 1768311 | AG28: 1500000
B29: Off-grid Connections Target (Mini-grids) | C29: M300 National Energy Compacts | X29: 115301
B30: Off-grid Connections Target (Solar kits) | C30: M300 National Energy Compacts | X30: 690392
B31: Off-grid Connections Target (HH) | C31: M300 National Energy Compacts | W31: 35000 | AA31: 800 | AC31: 560000
B32: Mini-grid Sites Target (count) | C32: M300 National Energy Compacts | E32: 6 | F32: 300 | N32: 400 | O32: 714 | U32: 120 | X32: 115301 | AB32: 150
B33: Mini-grid Capacity Target (MW) | C33: M300 National Energy Compacts | F33: 300 | AB33: 50
B34: SHS Connections Target (connections) | C34: M300 National Energy Compacts | F34: 850000 | H34: 30000 | N34: 1000000 | R34: 49441 | T34: 244000 | V34: 175235 | X34: 690392 | AB34: 300000 | AC34: 400000 | AD34: 133000
A35: Finance | B35: Total Investment Required (USD) | C35: M300 National Energy Compacts | D35: 2360000000 | E35: 2520000000 | F35: 3490000000 | G35: 12554000000 | H35: 1950000000 | I35: 390210000 | J35: 8460000000 | K35: 37048660000 | L35: 9646040 | M35: 552000000 | N35: 4404000000 | O35: 8900000000 | P35: 19115000000 | Q35: 1970000000 | R35: 1500000000 | S35: 7200000000 | T35: 5500000000 | U35: 3067300000 | V35: 18620000000 | W35: 1764000000 | Y35: 32700000000 | Z35: 11543000000 | AA35: 297000000 | AB35: 6300000000 | AC35: 2245000000 | AD35: 3000000000 | AE35: 12889999999 | AF35: 11880000 | AG35: 9134890000
B36: Public Financing Required (USD) | C36: M300 National Energy Compacts | D36: 1420000000 | E36: 1414000000 | F36: 1950000000 | G36: 1588000000 | H36: 1299744000 | I36: 117000000 | J36: 4620000000 | K36: 17314100000 | L36: 6584240 | M36: 305000000 | N36: 1793000 | O36: 1200000000 | P36: 14002000000 | Q36: 499700000 | R36: 1150000000 | U36: 1220260000 | V36: 9923000000 | W36: 1353000000 | Y36: 17200000000 | Z36: 3276000000 | AA36: 108000000 | AB36: 3926000000 | AC36: 835000000 | AD36: 1320000000 | AE36: 8850000000
B37: Private Financing Required (USD) | C37: M300 National Energy Compacts | D37: 940000000 | E37: 1106000000 | F37: 1540000000 | G37: 6372000000 | H37: 650256000 | I37: 273000000 | J37: 1940000000 | K37: 19734550000 | L37: 3061800 | M37: 247000000 | N37: 2611000 | O37: 7641000000 | P37: 5113000000 | Q37: 1470000000 | R37: 140000000 | T37: 162800000 | U37: 1225800000 | V37: 8698000000 | W37: 411000000 | X37: 527000000 | Y37: 15500000000 | Z37: 8267000000 | AA37: 190000000 | AB37: 2300000000 | AC37: 1410000000 | AD37: 1680000000 | AE37: 4039000000 | AF37: 9500000000 | AG37: 4420000000
B38: World Bank Financing (USD) | C38: M300 National Energy Compacts | N38: 260000000 | Q38: 52900000 | R38: 200000000
B39: AfDB Financing (USD) | C39: M300 National Energy Compacts | N39: 85000000 | Q39: 10600000
B40: Other Donor Financing (USD) | C40: M300 National Energy Compacts | I40: 101400000 | T40: 530800000 | U40: 621240000
A41: Utility & Tariffs | B41: Average Tariff (USD/kWh) | C41: M300 National Energy Compacts | H41: 0.175 | I41: 0.43 | K41: 0.09 | M41: 0.21 | O41: 0.1 | R41: 0.23 | X41: 0.14 | Y41: 0.09 | Z41: 0.09 | AC41: 0.21 | AE41: 0.089 | AG41: 0.1608
B42: Cost Recovery Ratio current | C42: M300 National Energy Compacts | I42: 56.6 | L42: 60 | O42: 45 | Z42: 0.56 | AB42: 0.72
B43: Cost Recovery Ratio target | C43: M300 National Energy Compacts | AG43: 1
B44: Utility Collection Rate - Current (%) | C44: M300 National Energy Compacts | G44: 72 | H44: 51 | I44: 80 | K44: 61 | N44: 86 | S44: 80 | Z44: 73 | AE44: 96
B45: Utility Collection Rate - Target (%) | C45: M300 National Energy Compacts | G45: 90 | H45: 45 | I45: 90 | L45: 90 | S45: 90 | Z45: 95 | AB45: 100
A46: Renewables, Climate & Efficiency | B46: Renewable Share – Current (%) | C46: M300 National Energy Compacts | D46: 16 | E46: 8.2 | F46: 83 | I46: 9 | J46: 31 | K46: 95 | L46: 95 | M46: 13 | N46: 4 | O46: 62 | P46: 83 | Q46: 99.6 | R46: 67 | S46: 45 | T46: 90 | U46: 44.36 | V46: 78.4 | W46: 54 | X46: 5 | Y46: 22 | Z46: 29 | AA46: 5 | AB46: 29 | AC46: 46 | AD46: 26 | AE46: 61.8 | AF46: 86.2 | AG46: 43
B47: Renewable Share – 2030 Target (%) | C47: M300 National Energy Compacts | D47: 30 | E47: 50 | F47: 99 | G47: 10 | H47: 30 | I47: 45 | J47: 45 | K47: 95 | M47: 30 | N47: 10 | O47: 70 | P47: 100 | Q47: 100 | R47: 75 | S47: 85 | T47: 96.1 | U47: 70 | V47: 80.6 | W47: 70 | X47: 30 | Y47: 50 | Z47: 72.8 | AA47: 50 | AB47: 40 | AC47: 52 | AD47: 63 | AE47: 75 | AG47: 48.6
B48: CO2 Emissions Reduction (tCO2) | C48: M300 National Energy Compacts | F48: 343720000000 | J48: 6319428 | T48: 4090750 | U48: 1400000
B49: Energy Efficiency Savings (GWh/year) | C49: M300 National Energy Compacts
A50: Clean Cooking | B50: Clean cooking access - current (%) | C50: M300 National Energy Compacts | D50: 10.5 | E50: 66.6 | G50: 23.4 | I50: 0.5 | J50: 20 | K50: 5 | L50: 8 | M50: 25 | N50: 36.9 | O50: 12 | P50: 34.4 | Q50: 45.2 | R50: 0.8 | S50: 14 | T50: 24.5 | U50: 54 | V50: 17 | W50: 48.5 | X50: 6 | Y50: 26 | Z50: 39.6 | AA50: 62 | AC50: 1.5 | AD50: 14 | AE50: 6.9 | AF50: 8.9 | AG50: 38.6
B51: Clean cooking access, urban - current (%) | C51: M300 National Energy Compacts | E51: 86.9 | W51: 77.1 | Z51: 54.5
B52: Clean cooking access, rural - current (%) | C52: M300 National Energy Compacts | E52: 25.3 | W52: 13.8 | Z52: 4.7
B53: Clean cooking access by electricity - current (%) | C53: M300 National Energy Compacts | E53: 24.4 | P53: 1.3 | T53: 1.7 | Y53: 1 | AA53: 0.08 | AB53: 0.1 | AC53: 0 | AF53: 15.8
B54: Clean cooking access by biogas - current (%) | C54: M300 National Energy Compacts | P54: 0.3 | T54: 0
B55: Clean cooking access by LPG - current (%) | C55: M300 National Energy Compacts | E55: 42.7 | J55: 20 | N55: 31 | P55: 30.7 | T55: 0.3 | V55: 14 | W55: 21.8 | X55: 4.6 | Y55: 10.5 | AA55: 18.9 | AB55: 34 | AC55: 0.9 | AE55: 3.2 | AF55: 0.3
B56: Clean cooking access by bioethanol - current (%) | C56: M300 National Energy Compacts | P56: 1.8 | T56: 0 | AC56: 0 | AF56: 0.1
B57: Clean cooking access by other technologies - current (%) | C57: M300 National Energy Compacts | V57: 3.4
B58: Clean cooking access - 2030 target (%) | C58: M300 National Energy Compacts | D58: 50 | E58: 90 | F58: 40 | G58: 40 | H58: 46 | I58: 30 | J58: 50 | K58: 30 | L58: 57.74 | M58: 50 | N58: 50 | O58: 35 | P58: 100 | Q58: 75 | S58: 50 | T58: 75 | V58: 54 | W58: 61 | X58: 12 | Y58: 100 | Z58: 81.3 | AA58: 75 | AC58: 25 | AD58: 80 | AE58: 75 | AF58: 40 | AG58: 70
B59: Clean cooking access - 2030 target (persons) | C59: M300 National Energy Compacts
B60: Population with clean cooking access (%) | C60: M300 National Energy Compacts | E60: 66 | N60: 36.9 | O60: 12 | P60: 34.4 | Q60: 45.2 | R60: 0.8 | S60: 14 | T60: 24.5 | U60: 54 | V60: 17 | W60: 48.5 | X60: 4.6 | Y60: 26 | Z60: 39.6 | AA60: 62 | AE60: 6.9
B61: Total people with clean cooking access (additional persons) | C61: M300 National Energy Compacts | F61: 6000000 | G61: 13400000 | K61: 40000000 | N61: 3100000 | P61: 4800000 | R61: 9545 | S61: 4100000 | AB61: 15800000
B62: Total people with clean cooking access (households) | C62: M300 National Energy Compacts | D62: 1285000 | F62: 1200000 | H62: 5500000 | J62: 2400000 | K62: 5000000 | P62: 15000000 | S62: 800000 | V62: 4500000 | AC62: 900000
A63: Compact Timeline | B63: Compact Start Year | C63: M300 National Energy Compacts | D63: 2025 | E63: 2025 | F63: 2025 | G63: 2025 | H63: 2025 | I63: 2025 | J63: 2025 | K63: 2025 | L63: 2024 | M63: 2024 | N63: 2025 | O63: 2025 | P63: 2025 | Q63: 2024 | R63: 2024 | S63: 2024 | T63: 2024 | U63: 2024 | V63: 2024 | W63: 2025 | X63: 2024 | Y63: 2024 | Z63: 2025 | AA63: 2024 | AB63: 2024 | AC63: 2025 | AD63: 2025 | AE63: 2024 | AF63: 2025 | AG63: 2025
B64: Compact End Year | C64: M300 National Energy Compacts | D64: 2030 | E64: 2030 | F64: 2030 | G64: 2030 | H64: 2030 | I64: 2030 | J64: 2030 | K64: 2030 | L64: 2030 | M64: 2030 | N64: 2030 | O64: 2030 | P64: 2030 | Q64: 2030 | R64: 2030 | S64: 2030 | T64: 2030 | U64: 2030 | V64: 2030 | W64: 2030 | X64: 2030 | Y64: 2030 | Z64: 2030 | AA64: 2030 | AB64: 2030 | AC64: 2030 | AD64: 2030 | AE64: 2030 | AF64: 2030 | AG64: 2030
B65: Universal Access Target Year | C65: M300 National Energy Compacts | D65: 2030 | E65: 2030 | F65: 2030 | G65: 2030 | H65: 2030 | I65: 2030 | J65: 2030 | K65: 2030 | L65: 2030 | M65: 2030 | N65: 2030 | O65: 2030 | P65: 2030 | Q65: 2030 | R65: 2030 | S65: 2030 | T65: 2030 | U65: 2030 | V65: 2030 | W65: 2040 | X65: 2030 | Y65: 2030 | Z65: 2030 | AA65: 2030 | AB65: 2029 | AC65: 2030 | AD65: 2030 | AE65: 2030 | AF65: 2030 | AG65: 2030
A66: Population | B66: 2024 population (million) | C66: World Bank Open Database | D66: 14.5 | E66: 2.5 | F66: 14 | G66: 29.1 | H66: 20.3 | I66: 0.9 | J66: 31.9 | K66: 109.3 | L66: 132.1 | M66: 2.8 | N66: 34.4 | O66: 14.8 | P66: 56.4 | Q66: 2.3 | R66: 5.6 | S66: 32 | T66: 21.7 | U66: 5.2 | V66: 34.6 | W66: 3 | X66: 27 | Y66: 232.7 | Z66: 6.3 | AA66: 0.2 | AB66: 18.5 | AC66: 8.6 | AD66: 9.5 | AE66: 68.6 | AF66: 21.3 | AG66: 16.6
B67: 2030 Projected population (million) | C67: UN World Population Prospects | D67: =16618822/1000000 -> 16.618822 | E67: =2765917.5/1000000 -> 2.7659175 | F67: =16182016.5/1000000 -> 16.182016 | G67: =33777189.5/1000000 -> 33.777189 | H67: =24207479/1000000 -> 24.207479 | I67: =964264.5/1000000 -> 0.9642645 | J67: =36699009/1000000 -> 36.699009 | K67: =131532201/1000000 -> 131.5322 | L67: =152855357/1000000 -> 152.85536 | M67: =3130133.5/1000000 -> 3.1301335 | N67: =38222089/1000000 -> 38.222089 | O67: =16807147/1000000 -> 16.807147 | P67: =63102245.5/1000000 -> 63.102246 | Q67: =2493818.5/1000000 -> 2.4938185 | R67: =6366291/1000000 -> 6.366291 | S67: =36693183/1000000 -> 36.693183 | T67: =25160287.5/1000000 -> 25.160287 | U67: =6062528/1000000 -> 6.062528 | V67: =40846754.5/1000000 -> 40.846755 | W67: =3389958/1000000 -> 3.389958 | X67: =32518075/1000000 -> 32.518075 | Y67: =262380969.5/1000000 -> 262.38097 | Z67: =7282266.5/1000000 -> 7.2822665 | AA67: =264564.5/1000000 -> 0.2645645 | AB67: =21163191.5/1000000 -> 21.163191 | AC67: =9694858/1000000 -> 9.694858 | AD67: =10792997/1000000 -> 10.792997 | AE67: =80913124/1000000 -> 80.913124 | AF67: =25024901/1000000 -> 25.024901 | AG67: =18610348.5/1000000 -> 18.610349

Sheet Qualitative
A1: Scoring legend:
A2: 0 = Not mentioned
A3: 1 = Mentioned
A4: 2 = Operationalised (actions, reforms, or institutions named)
B5: Benin | C5: Botswana | D5: Burundi | E5: Cameroon | F5: Chad | G5: Comoros | H5: Côte d’Ivoire | I5: DRC | J5: Ethiopia | K5: Gambia | L5: Ghana | M5: Guinea | N5: Kenya | O5: Lesotho | P5: Liberia | Q5: Madagascar | R5: Malawi | S5: Mauritania | T5: Mozambique | U5: Namibia | V5: Niger | W5: Nigeria | X5: Republic of Congo | Y5: São Tomé & Príncipe | Z5: Senegal | AA5: Sierra Leone | AB5: Togo | AC5: Tanzania | AD5: Zambia | AE5: Zimbabwe
A6: National definition of electricity access stated | B6: 2
A7: National definition of electricity access stated | B7: 2
A8: Alignment with SDG 7 electricity access definition | B8: 2
A9: Treatment of reliability and quality of electricity supply | B9: 1
A10: Recognition of suppressed or latent electricity demand | B10: 2
A11: Explicit rationale for urban–rural access differentiation | B11: 2
A12: Priority regions or populations explicitly identified | B12: 1
A13: Integration of population growth assumptions in access planning | B13: 1
A14: Consideration of productive-use electricity demand | B14: 2
A15: Explicit prioritisation between grid, mini-grid, and off-grid solutions | B15: 2
A16: Use of least-cost or geospatial electrification planning | B16: 2
A17: Assumptions underpinning installed capacity expansion targets | B17: 2
... A55: Explicit risks and implementation constraints acknowledged | B55: 2
A56: Overall realism and credibility of stated targets

Sheet Qual_Ref
B2: Benin | C2: Botswana | D2: Burundi | E2: Cameroon | F2: Chad | G2: Comoros | H2: Côte d’Ivoire | I2: DRC | J2: Ethiopia | K2: Gambia | L2: Ghana | M2: Guinea | N2: Kenya | O2: Lesotho | P2: Liberia | Q2: Madagascar | R2: Malawi | S2: Mauritania | T2: Mozambique | U2: Namibia | V2: Niger | W2: Nigeria | X2: Republic of Congo | Y2: São Tomé & Príncipe | Z2: Senegal | AA2: Sierra Leone | AB2: Togo | AC2: Tanzania | AD2: Zambia | AE2: Zimbabwe
A3: National definition of electricity access stated | B3: Defines access as “ensemble des ménages ayant accès à l’électricité intégrant les raccordements au réseau, les mini-réseaux et les kits” (footnote defining access; p.2).
A4: National definition of electricity access stated | B4: Explicit alignment with ODD 7 and definition of reliable, affordable, modern energy (p.2).
A5: Alignment with SDG 7 electricity access definition | B5: Repeated use of “électricité fiable, abordable et suffisante” and operational actions: SCADA, smart meters, storage, loss reduction (pp.6–8, 17–25).
A6: Treatment of reliability and quality of electricity supply | B6: Implicit via references to rising demand from mobility, cooking, and growth, but not framed as “suppressed demand” (Table 5, p.15).
A7: Recognition of suppressed or latent electricity demand | B7: Explicit last-mile focus, rural electrification funds (FERER), mini-grids and SHS for off-grid areas (Pillar III).
A8: Explicit rationale for urban–rural access differentiation | B8: Regional breakdowns (Zone Sud / Zone Nord) and rural/off-grid households identified for programmes (pp.17–18).
A9: Priority regions or populations explicitly identified | B9: Population numbers used for access targets, but growth dynamics not explicitly modelled (Table 2, p.11).
A10: Integration of population growth assumptions in access planning | B10: Mention of mobility, industry, and economic growth drivers without explicit PUE strategy (Table 5, p.15).
A11: Consideration of productive-use electricity demand | B11: Clear quantitative targets by modality (Table 3, p.12).
A12: Explicit prioritisation between grid, mini-grid, and off-grid solutions | B12: Explicit use of SIG électrique and geospatial prioritisation (pp.16–18).
A13: Use of least-cost or geospatial electrification planning | B13: Detailed MW targets for solar, thermal, storage, and timelines (pp.15–16).
A14: Assumptions underpinning installed capacity expansion targets | B14: Renewables for sustainability; thermal for reliability and baseload (Pillars I–II).
... A52: Explicit risks and implementation constraints acknowledged | B52: Detailed targets, financing, institutions → high credibility.
A53: Overall realism and credibility of stated targets

Sheet Source_Data
A1: Country | B1: Indicator | C1: Value (as stated in National Energy Compact) | D1: Status | E1: Notes
A2: Benin | B2: Current Electricity Access Rate (%) | C2: 42.6% (2024) | D2: ✅ Fully usable
A3: Benin | B3: Current Urban Electricity Access Rate (%) | C3: 0.712 | D3: ✅ Fully usable
A4: Benin | B4: Current Rural Electricity Access Rate (%) | C4: 0.131 | D4: ✅ Fully usable
A5: Benin | B5: Target Electricity Access Rate by 2030 (%) | C5: 0.7 | D5: ✅ Fully usable
A6: Benin | B6: Target Urban Electricity Access Rate by 2030 (%) | C6: Not stated | D6: ❌ Completely absent
A7: Benin | B7: Target Rural Electricity Access Rate by 2030 (%) | C7: Not stated | D7: ❌ Completely absent
A8: Benin | B8: Population Without Electricity (people) | C8: Not stated | D8: ⚠️ Implicitly referenced
A9: Benin | B9: Installed Capacity – Current (MW) | C9: 199 MW | D9: ✅ Fully usable
A10: Benin | B10: Installed Capacity – 2030 Target (MW) | C10: 794 MW | D10: ✅ Fully usable
A11: Benin | B11: New Generation Required (MW) | C11: Not stated | D11: ⚠️ Implicitly referenced
A12: Benin | B12: Renewable Capacity – Current (MW) | C12: 62.3 MW | D12: ✅ Fully usable
A13: Benin | B13: Renewable Capacity – 2030 Target (MW) | C13: 417 MW | D13: ✅ Fully usable
A14: Benin | B14: Solar Capacity Target (MW) | C14: Not stated (projects only) | D14: ⚠️ Implicitly referenced
A15: Benin | B15: Wind Capacity Target (MW) | C15: Not stated | D15: ❌ Completely absent
A16: Benin | B16: Hydro Capacity Target (MW) | C16: Not stated | D16: ⚠️ Implicitly referenced
A17: Benin | B17: Gas Capacity Target (MW) | C17: Not stated as target | D17: ⚠️ Implicitly referenced
... A30: Benin | B30: SHS Connections Target (connections) | C30: Not stated as single target | D30: ⚠️ Implicitly referenced
A31: Benin | B31: Total Investment Required (EUR) | C31: 2362470000 | D31: ✅ Fully usable
A32: Benin | B32: Total Investment Required (USD) | C32: ≈ USD 2,360,000,000 | D32: ⚠️ Approximate
A33: Benin | B33: Public Financing Required (EUR) | C33: 1424080000 | D33: ✅ Fully usable
A34: Benin | B34: Public Financing Required (USD) | C34: ≈ USD 1,420,000,000 | D34: ⚠️ Approximate
A35: Benin | B35: Private Financing Required (EUR) | C35: 938390000 | D35: ✅ Fully usable
A36: Benin | B36: Private Financing Required (USD) | C36: ≈ USD 940,000,000 | D36: ⚠️ Approximate
A37: Benin | B37: World Bank Financing (USD) | C37: Not stated | D37: ❌ Completely absent
A38: Benin | B38: AfDB Financing (USD) | C38: Not stated | D38: ❌ Completely absent
A39: Benin | B39: Other Donor Financing (USD) | C39: Not stated | D39: ❌ Completely absent
A40: Benin | B40: Average Tariff (USD/kWh) | C40: Not stated | D40: ❌ Completely absent
A41: Benin | B41: Cost Recovery Ratio | C41: Policy target ≥100% | D41: ⚠️ Implicitly referenced
A42: Benin | B42: Utility Collection Rate (%) | C42: Target ≥95% (zones) | D42: ⚠️ Implicitly referenced
A43: Benin | B43: Renewable Share – Current (%) | C43: 0.16 | D43: ✅ Fully usable
A44: Benin | B44: Renewable Share – 2030 Target (%) | C44: 0.3 | D44: ✅ Fully usable
A45: Benin | B45: CO₂ Emissions Reduction (tCO₂) | C45: Not stated | D45: ❌ Completely absent
A46: Benin | B46: Energy Efficiency Savings (GWh/year) | C46: Not stated | D46: ❌ Completely absent
A47: Benin | B47: Clean cooking access – current (%) | C47: 0.105 | D47: ✅ Fully usable
A48: Benin | B48: Clean cooking access, urban – current (%) | C48: Not stated | D48: ❌ Completely absent
A49: Benin | B49: Clean cooking access, rural – current (%) | C49: Not stated | D49: ❌ Completely absent
A50: Benin | B50: Clean cooking access by electricity – current (%) | C50: Not stated | D50: ❌ Completely absent
A51: Benin | B51: Clean cooking access by biogas – current (%) | C51: Not stated | D51: ❌ Completely absent
A52: Benin | B52: Clean cooking access by LPG – current (%) | C52: Not stated | D52: ❌ Completely absent
A53: Benin | B53: Clean cooking access by bioethanol – current (%) | C53: Not stated | D53: ❌ Completely absent
A54: Benin | B54: Clean cooking access – 2030 target (%) | C54: 50% of households | D54: ✅ Fully usable
A55: Benin | B55: Population with clean cooking access (%) | C55: Not stated | D55: ❌ Completely absent
A56: Benin | B56: Total people with clean cooking access (persons) | C56: Not stated | D56: ❌ Completely absent
A57: Benin | B57: Total people with clean cooking access (households) | C57: 1,285,000 households | D57: ✅ Fully usable
A58: Benin | B58: Compact Start Year | C58: 2025 | D58: ✅ Fully usable
A59: Benin | B59: Compact End Year | C59: 2030 | D59: ✅ Fully usable
A60: Benin | B60: Universal Access Target Year | C60: 2030 | D60: ✅ Fully usable
A61: Botswana | B61: Current Electricity Access Rate (%) | C61: 76.6% (2024/25) | D61: ✅ Fully usable
A62: Botswana | B62: Current Urban Electricity Access Rate (%) | C62: >90% | D62: ⚠️ Implicitly referenced
A63: Botswana | B63: Current Rural Electricity Access Rate (%) | C63: Not stated numerically | D63: ❌ Completely absent
A64: Botswana | B64: Target Electricity Access Rate by 2030 (%) | C64: 1 | D64: ✅ Fully usable
A65: Botswana | B65: Target Urban Electricity Access Rate by 2030 (%) | C65: Not stated | D65: ❌ Completely absent
A66: Botswana | B66: Target Rural Electricity Access Rate by 2030 (%) | C66: Not stated | D66: ❌ Completely absent
A67: Botswana | B67: Population Without Electricity (people) | C67: ~24% of population | D67: ⚠️ Implicitly referenced
A68: Botswana | B68: Installed Capacity – Current (MW) | C68: 892 MW (March 2025) | D68: ✅ Fully usable
A69: Botswana | B69: Installed Capacity – 2030 Target (MW) | C69: 950 MW (domestic) / 1,850 MW (with exports) | D69: ✅ Fully usable
A70: Botswana | B70: New Generation Required (MW) | C70: Not stated | D70: ⚠️ Implicitly referenced
A71: Botswana | B71: Renewable Capacity – Current (MW) | C71: 74.6 MW | D71: ✅ Fully usable
A72: Botswana | B72: Renewable Capacity – 2030 Target (MW) | C72: 475 MW (domestic) / 1,850 MW (export scenario) | D72: ✅ Fully usable
A73: Botswana | B73: Solar Capacity Target (MW) | C73: 1,500 MW by 2030 | D73: ✅ Fully usable
A74: Botswana | B74: Wind Capacity Target (MW) | C74: 100 MW | D74: ✅ Fully usable
A75: Botswana | B75: Hydro Capacity Target (MW) | C75: Not stated | D75: ❌ Completely absent
A76: Botswana | B76: Gas Capacity Target (MW) | C76: Not stated | D76: ❌ Completely absent
... A99: Botswana | B99: Renewable Share – Current (%) | C99: 7–8.2% | D99: ⚠️ Implicitly referenced
A100: Botswana | B100: Renewable Share – 2030 Target (%) | C100: 0.5 | D100: ✅ Fully usable
A101: Botswana | B101: CO₂ Emissions Reduction (tCO₂) | C101: Not stated | D101: ❌ Completely absent
A102: Botswana | B102: Energy Efficiency Savings (GWh/year) | C102: Not stated | D102: ❌ Completely absent
A103: Botswana | B103: Clean cooking access – current (%) | C103: 66.6% (2021/22) | D103: ✅ Fully usable
A104: Botswana | B104: Clean cooking access, urban – current (%) | C104: 0.869 | D104: ✅ Fully usable
A105: Botswana | B105: Clean cooking access, rural – current (%) | C105: 0.253 | D105: ✅ Fully usable
A106: Botswana | B106: Clean cooking access by electricity – current (%) | C106: 0.244 | D106: ✅ Fully usable
A107: Botswana | B107: Clean cooking access by biogas – current (%) | C107: Not stated | D107: ❌ Completely absent
A108: Botswana | B108: Clean cooking access by LPG – current (%) | C108: 0.427 | D108: ✅ Fully usable
A109: Botswana | B109: Clean cooking access by bioethanol – current (%) | C109: Not stated | D109: ❌ Completely absent
A110: Botswana | B110: Clean cooking access – 2030 target (%) | C110: 0.9 | D110: ✅ Fully usable
A111: Botswana | B111: Population with clean cooking access (%) | C111: 0.66 | D111: ✅ Fully usable
A112: Botswana | B112: Total people with clean cooking access (persons) | C112: Not stated | D112: ❌ Completely absent
A113: Botswana | B113: Total people with clean cooking access (households) | C113: ~420,000 households | D113: ⚠️ Implicitly referenced
A114: Botswana | B114: Compact Start Year | C114: 2025 | D114: ✅ Fully usable
A115: Botswana | B115: Compact End Year | C115: 2030 | D115: ✅ Fully usable
A116: Botswana | B116: Universal Access Target Year | C116: 2030 | D116: ✅ Fully usable
A117: Burundi | B117: Current Electricity Access Rate (%) | C117: 25.9% (2025) | D117: ✅ Fully usable
A118: Burundi | B118: Current Urban Electricity Access Rate (%) | C118: 0.663 | D118: ✅ Fully usable
A119: Burundi | B119: Current Rural Electricity Access Rate (%) | C119: 0.176 | D119: ✅ Fully usable
A120: Burundi | B120: Target Electricity Access Rate by 2030 (%) | C120: 0.7 | D120: ✅ Fully usable
A121: Burundi | B121: Target Urban Electricity Access Rate by 2030 (%) | C121: Not stated | D121: ❌ Completely absent
A122: Burundi | B122: Target Rural Electricity Access Rate by 2030 (%) | C122: Not stated | D122: ❌ Completely absent
A123: Burundi | B123: Population Without Electricity (people) | C123: ≈ 11.6 million people | D123: ✅ Fully usable
A124: Burundi | B124: Installed Capacity – Current (MW) | C124: 204.882 MW (2025) | D124: ✅ Fully usable
A125: Burundi | B125: Installed Capacity – 2030 Target (MW) | C125: 410 MW (domestic) | D125: ✅ Fully usable
A126: Burundi | B126: New Generation Required (MW) | C126: Not stated | D126: ⚠️ Implicitly referenced
A127: Burundi | B127: Renewable Capacity – Current (MW) | C127: Not stated as MW | D127: ⚠️ Implicitly referenced
A128: Burundi | B128: Renewable Capacity – 2030 Target (MW) | C128: Not stated as MW | D128: ⚠️ Implicitly referenced
A129: Burundi | B129: Solar Capacity Target (MW) | C129: ≈ 254 MW (projects in plan) | D129: ⚠️ Implicitly referenced
A130: Burundi | B130: Wind Capacity Target (MW) | C130: Not stated | D130: ❌ Completely absent
A131: Burundi | B131: Hydro Capacity Target (MW) | C131: ≈ 155.5 MW (named projects) | D131: ⚠️ Implicitly referenced
A132: Burundi | B132: Gas Capacity Target (MW) | C132: Not stated | D132: ❌ Completely absent
... A154: Burundi | B154: Utility Collection Rate (%) | C154: Not stated | D154: ❌ Completely absent
A155: Burundi | B155: Renewable Share – Current (%) | C155: 0.83 | D155: ✅ Fully usable
...
